{"date": "2025-04-05", "hottest": [{"title": "YimMenuV2 E&E with money cheat &#40;No FSL&#41;", "link": "https://%75%6E%6B%6E%6F%77%6E%63%68%65%61%74%73.%6D%65/%66%6F%72%75%6D/grand-theft-auto-v/694886-yimmenuv2-money-cheat-fsl.html", "date": "2025-04-05 00:10:55", "forum": "grand-theft-auto-v", "reply": "64"}, {"title": "External GlowESP &#40;with source code&#41;", "link": "https://%75%6E%6B%6E%6F%77%6E%63%68%65%61%74%73.%6D%65/%66%6F%72%75%6D/counter-strike-2-a/694365-external-glowesp-source-code.html", "date": "2025-04-05 00:10:55", "forum": "counter-strike-2-a", "reply": "42"}, {"title": "33 Immortals &#40;Gamepass version&#41;", "link": "https://%75%6E%6B%6E%6F%77%6E%63%68%65%61%74%73.%6D%65/%66%6F%72%75%6D/other-games/694162-33-immortals-gamepass-version.html", "date": "2025-04-05 00:10:55", "forum": "other-games", "reply": "26"}, {"title": "V\u00eanus AimColor FragPunk", "link": "https://%75%6E%6B%6E%6F%77%6E%63%68%65%61%74%73.%6D%65/%66%6F%72%75%6D/other-fps-games/694226-nus-aimcolor-fragpunk.html", "date": "2025-04-05 00:10:55", "forum": "other-fps-games", "reply": "43"}, {"title": "mod&#95;au", "link": "https://%75%6E%6B%6E%6F%77%6E%63%68%65%61%74%73.%6D%65/%66%6F%72%75%6D/among-us/694266-mod_au.html", "date": "2025-04-05 00:10:55", "forum": "among-us", "reply": "13"}, {"title": "FiveM External Self Leak &#40;1604 to 3274&#41;", "link": "https://%75%6E%6B%6E%6F%77%6E%63%68%65%61%74%73.%6D%65/%66%6F%72%75%6D/alternative-online-mods/694182-fivem-external-self-leak-1604-3274-a.html", "date": "2025-04-05 00:10:55", "forum": "alternative-online-mods", "reply": "11"}, {"title": "Language", "link": "https://%75%6E%6B%6E%6F%77%6E%63%68%65%61%74%73.%6D%65/%66%6F%72%75%6D/programming-for-beginners/694023-language.html", "date": "2025-04-05 00:10:55", "forum": "programming-for-beginners", "reply": "2"}, {"title": "help define the enemy", "link": "https://%75%6E%6B%6E%6F%77%6E%63%68%65%61%74%73.%6D%65/%66%6F%72%75%6D/warface/694129-help-define-enemy.html", "date": "2025-04-05 00:10:55", "forum": "warface", "reply": "0"}, {"title": "GMS V258&#46;2", "link": "https://%75%6E%6B%6E%6F%77%6E%63%68%65%61%74%73.%6D%65/%66%6F%72%75%6D/maple-story/694200-gms-v258-2-a.html", "date": "2025-04-05 00:10:55", "forum": "maple-story", "reply": "3"}, {"title": "SeownedDE x64 2025/3/29&#40;rei2&#41;", "link": "https://%75%6E%6B%6E%6F%77%6E%63%68%65%61%74%73.%6D%65/%66%6F%72%75%6D/team-fortress-2-a/694048-seownedde-x64-2025-3-29-rei2.html", "date": "2025-04-05 00:10:55", "forum": "team-fortress-2-a", "reply": "8"}, {"title": "How can I find GWorld offset?", "link": "https://%75%6E%6B%6E%6F%77%6E%63%68%65%61%74%73.%6D%65/%66%6F%72%75%6D/all-points-bulletin/694190-gworld-offset.html", "date": "2025-04-05 02:48:18", "forum": "all-points-bulletin", "reply": "6"}], "files": [{"title": "Fortnite external&#46;exe", "link": "https://%75%6E%6B%6E%6F%77%6E%63%68%65%61%74%73.%6D%65/%66%6F%72%75%6D/downloads.php?do=file&id=49256", "date": "2025-04-05 00:10:55", "downloads": "32"}, {"title": "MW19 Op codes CW/VG/MW", "link": "https://%75%6E%6B%6E%6F%77%6E%63%68%65%61%74%73.%6D%65/%66%6F%72%75%6D/downloads.php?do=file&id=49251", "date": "2025-04-05 00:10:55", "downloads": "3"}, {"title": "VAL 10&#46;06 SDK", "link": "https://%75%6E%6B%6E%6F%77%6E%63%68%65%61%74%73.%6D%65/%66%6F%72%75%6D/downloads.php?do=file&id=49245", "date": "2025-04-05 00:10:55", "downloads": "73"}, {"title": "My Hero Ultra Rumble V15 Hitlerjoe&#46;CT", "link": "https://%75%6E%6B%6E%6F%77%6E%63%68%65%61%74%73.%6D%65/%66%6F%72%75%6D/downloads.php?do=file&id=49242", "date": "2025-04-05 00:10:55", "downloads": "54"}, {"title": "Kappa Item Checker", "link": "https://%75%6E%6B%6E%6F%77%6E%63%68%65%61%74%73.%6D%65/%66%6F%72%75%6D/downloads.php?do=file&id=49240", "date": "2025-04-05 00:10:55", "downloads": "3"}, {"title": "EXTERNAL CHEAT", "link": "https://%75%6E%6B%6E%6F%77%6E%63%68%65%61%74%73.%6D%65/%66%6F%72%75%6D/downloads.php?do=file&id=49236", "date": "2025-04-05 00:10:55", "downloads": "469"}, {"title": "Offsets for EXTERNAL CHEAT", "link": "https://%75%6E%6B%6E%6F%77%6E%63%68%65%61%74%73.%6D%65/%66%6F%72%75%6D/downloads.php?do=file&id=49233", "date": "2025-04-05 00:10:55", "downloads": "50"}, {"title": "cheat&#46;exe", "link": "https://%75%6E%6B%6E%6F%77%6E%63%68%65%61%74%73.%6D%65/%66%6F%72%75%6D/downloads.php?do=file&id=49231", "date": "2025-04-05 00:10:55", "downloads": "150"}, {"title": "dunecore&#95;1&#46;5&#46;1&#95;updated", "link": "https://%75%6E%6B%6E%6F%77%6E%63%68%65%61%74%73.%6D%65/%66%6F%72%75%6D/downloads.php?do=file&id=49230", "date": "2025-04-05 00:10:55", "downloads": "50"}, {"title": "Kratos MDriver", "link": "https://%75%6E%6B%6E%6F%77%6E%63%68%65%61%74%73.%6D%65/%66%6F%72%75%6D/downloads.php?do=file&id=49229", "date": "2025-04-05 00:10:55", "downloads": "39"}, {"title": "Scedule 1 &#45; BlackjackCheat", "link": "https://%75%6E%6B%6E%6F%77%6E%63%68%65%61%74%73.%6D%65/%66%6F%72%75%6D/downloads.php?do=file&id=49239", "date": "2025-04-05 03:46:05", "downloads": "1"}, {"title": "Precum v1&#46;0&#46;0", "link": "https://%75%6E%6B%6E%6F%77%6E%63%68%65%61%74%73.%6D%65/%66%6F%72%75%6D/downloads.php?do=file&id=49238", "date": "2025-04-05 03:46:05", "downloads": "1"}, {"title": "mod&#95;au&#95;steam&#95;epic", "link": "https://%75%6E%6B%6E%6F%77%6E%63%68%65%61%74%73.%6D%65/%66%6F%72%75%6D/downloads.php?do=file&id=49235", "date": "2025-04-05 03:52:05", "downloads": "1"}, {"title": "SAR Offset finder ", "link": "https://%75%6E%6B%6E%6F%77%6E%63%68%65%61%74%73.%6D%65/%66%6F%72%75%6D/downloads.php?do=file&id=49254", "date": "2025-04-05 05:16:07", "downloads": "1"}, {"title": "SDK&#95;Steel&#95;Hunters&#95;04&#46;04&#46;2025", "link": "https://%75%6E%6B%6E%6F%77%6E%63%68%65%61%74%73.%6D%65/%66%6F%72%75%6D/downloads.php?do=file&id=49249", "date": "2025-04-05 05:16:07", "downloads": "1"}, {"title": "amalgam x64 latest", "link": "https://%75%6E%6B%6E%6F%77%6E%63%68%65%61%74%73.%6D%65/%66%6F%72%75%6D/downloads.php?do=file&id=49243", "date": "2025-04-05 05:28:23", "downloads": "1"}], "latest": [{"title": "Amalgam x64", "link": "https://%75%6E%6B%6E%6F%77%6E%63%68%65%61%74%73.%6D%65/%66%6F%72%75%6D/team-fortress-2-a/639800-amalgam-x64.html", "date": "2025-04-05 05:24:00", "forum": "Team Fortress 2"}, {"title": "VGK obfuscation", "link": "https://%75%6E%6B%6E%6F%77%6E%63%68%65%61%74%73.%6D%65/%66%6F%72%75%6D/anti-cheat-bypass/671176-vgk-obfuscation.html", "date": "2025-04-05 05:22:00", "forum": "Anti-Cheat Bypass"}, {"title": "Super Animal Royale Hack", "link": "https://%75%6E%6B%6E%6F%77%6E%63%68%65%61%74%73.%6D%65/%66%6F%72%75%6D/other-games/465314-super-animal-royale-hack.html", "date": "2025-04-05 05:04:00", "forum": "Other Games"}, {"title": "SteelHunters Reversal, Structs and Offsets", "link": "https://%75%6E%6B%6E%6F%77%6E%63%68%65%61%74%73.%6D%65/%66%6F%72%75%6D/other-fps-games/694888-steelhunters-reversal-structs-offsets.html", "date": "2025-04-05 05:02:00", "forum": "Other FPS Games"}, {"title": "PUBGM Lua Dump &#40;decompiled & decrypted&#41;", "link": "https://%75%6E%6B%6E%6F%77%6E%63%68%65%61%74%73.%6D%65/%66%6F%72%75%6D/pubg-mobile/694547-pubgm-lua-dump-decompiled-decrypted.html", "date": "2025-04-05 04:54:00", "forum": "PUBG Mobile"}, {"title": "Just Another Night Shift code enter cheat", "link": "https://%75%6E%6B%6E%6F%77%6E%63%68%65%61%74%73.%6D%65/%66%6F%72%75%6D/other-games/694400-night-shift-code-enter-cheat.html", "date": "2025-04-05 04:44:00", "forum": "Other Games"}, {"title": "Valorant Reversal, Structs and Offsets", "link": "https://%75%6E%6B%6E%6F%77%6E%63%68%65%61%74%73.%6D%65/%66%6F%72%75%6D/valorant/385792-valorant-reversal-structs-offsets.html", "date": "2025-04-05 04:42:00", "forum": "Valorant"}, {"title": "cs2 external cheat with source", "link": "https://%75%6E%6B%6E%6F%77%6E%63%68%65%61%74%73.%6D%65/%66%6F%72%75%6D/counter-strike-2-a/693925-cs2-external-cheat-source.html", "date": "2025-04-05 04:40:00", "forum": "Counter-Strike 2"}, {"title": "\ud83d\udc7d VALORANT Skin Changer &#40;Just Inject it&#33;&#41;", "link": "https://%75%6E%6B%6E%6F%77%6E%63%68%65%61%74%73.%6D%65/%66%6F%72%75%6D/valorant/517551-valorant-skin-changer-inject.html", "date": "2025-04-05 04:40:00", "forum": "Valorant"}, {"title": "Bypass question update", "link": "https://%75%6E%6B%6E%6F%77%6E%63%68%65%61%74%73.%6D%65/%66%6F%72%75%6D/counter-strike-2-a/694959-bypass-question-update.html", "date": "2025-04-05 04:38:00", "forum": "Counter-Strike 2"}, {"title": "TempleWare Internal CS2 Cheat", "link": "https://%75%6E%6B%6E%6F%77%6E%63%68%65%61%74%73.%6D%65/%66%6F%72%75%6D/counter-strike-2-releases/694796-templeware-internal-cs2-cheat.html", "date": "2025-04-05 04:33:00", "forum": "Counter-Strike 2 Releases"}, {"title": "working eac driver", "link": "https://%75%6E%6B%6E%6F%77%6E%63%68%65%61%74%73.%6D%65/%66%6F%72%75%6D/anti-cheat-bypass/695082-eac-driver.html", "date": "2025-04-05 04:30:00", "forum": "Anti-Cheat Bypass"}, {"title": "External Venus Aim", "link": "https://%75%6E%6B%6E%6F%77%6E%63%68%65%61%74%73.%6D%65/%66%6F%72%75%6D/other-fps-games/694984-external-venus-aim.html", "date": "2025-04-05 04:14:00", "forum": "Other FPS Games"}, {"title": "Path of Exile 2 Reversal, Structs and Offsets", "link": "https://%75%6E%6B%6E%6F%77%6E%63%68%65%61%74%73.%6D%65/%66%6F%72%75%6D/other-mmorpg-and-strategy/676435-path-exile-2-reversal-structs-offsets.html", "date": "2025-04-05 04:12:00", "forum": "Other MMORPG and Strategy"}, {"title": "Mordhau Lvl up cheat", "link": "https://%75%6E%6B%6E%6F%77%6E%63%68%65%61%74%73.%6D%65/%66%6F%72%75%6D/other-fps-games/695078-mordhau-lvl-cheat.html", "date": "2025-04-05 04:09:00", "forum": "Other FPS Games"}, {"title": "Controller Emulation", "link": "https://%75%6E%6B%6E%6F%77%6E%63%68%65%61%74%73.%6D%65/%66%6F%72%75%6D/call-of-duty-black-ops-6-a/673578-controller-emulation.html", "date": "2025-04-05 04:06:00", "forum": "Call of Duty: Black Ops 6"}, {"title": "BF3 Internal", "link": "https://%75%6E%6B%6E%6F%77%6E%63%68%65%61%74%73.%6D%65/%66%6F%72%75%6D/battlefield-3-a/695076-bf3-internal.html", "date": "2025-04-05 04:03:00", "forum": "Battlefield 3"}, {"title": "My Hero Ultra Rumble External", "link": "https://%75%6E%6B%6E%6F%77%6E%63%68%65%61%74%73.%6D%65/%66%6F%72%75%6D/other-games/670348-hero-ultra-rumble-external.html", "date": "2025-04-05 03:52:00", "forum": "Other Games"}, {"title": "mod&#95;au", "link": "https://%75%6E%6B%6E%6F%77%6E%63%68%65%61%74%73.%6D%65/%66%6F%72%75%6D/among-us/694266-mod_au.html", "date": "2025-04-05 03:46:00", "forum": "Among Us"}, {"title": "Apex Legends Reversal, Structs and Offsets", "link": "https://%75%6E%6B%6E%6F%77%6E%63%68%65%61%74%73.%6D%65/%66%6F%72%75%6D/apex-legends/319804-apex-legends-reversal-structs-offsets.html", "date": "2025-04-05 03:46:00", "forum": "Apex Legends"}, {"title": "List of Dev/Unobtainable Item IDs for item spawner", "link": "https://%75%6E%6B%6E%6F%77%6E%63%68%65%61%74%73.%6D%65/%66%6F%72%75%6D/escape-from-tarkov/658527-list-dev-unobtainable-item-ids-item-spawner.html", "date": "2025-04-05 03:30:00", "forum": "Escape from Tarkov"}, {"title": "How can i play valorant polygon without vanguard?", "link": "https://%75%6E%6B%6E%6F%77%6E%63%68%65%61%74%73.%6D%65/%66%6F%72%75%6D/valorant/694874-play-valorant-polygon-vanguard.html", "date": "2025-04-05 03:10:00", "forum": "Valorant"}, {"title": "Counter&#45;Strike 2 Reversal, Structs and Offsets", "link": "https://%75%6E%6B%6E%6F%77%6E%63%68%65%61%74%73.%6D%65/%66%6F%72%75%6D/counter-strike-2-a/576077-counter-strike-2-reversal-structs-offsets.html", "date": "2025-04-05 02:59:00", "forum": "Counter-Strike 2"}, {"title": "Undetectable among us Cheat&#33;", "link": "https://%75%6E%6B%6E%6F%77%6E%63%68%65%61%74%73.%6D%65/%66%6F%72%75%6D/among-us/637492-undetectable-cheat.html", "date": "2025-04-05 02:52:00", "forum": "Among Us"}, {"title": "New State Mobile", "link": "https://%75%6E%6B%6E%6F%77%6E%63%68%65%61%74%73.%6D%65/%66%6F%72%75%6D/pubg-mobile/694928-mobile.html", "date": "2025-04-05 02:33:00", "forum": "PUBG Mobile"}, {"title": "Valorant insta headshot AIMBOT&#91;UNDETECTED&#93;", "link": "https://%75%6E%6B%6E%6F%77%6E%63%68%65%61%74%73.%6D%65/%66%6F%72%75%6D/valorant/688675-valorant-insta-headshot-aimbot-undetected.html", "date": "2025-04-05 02:22:00", "forum": "Valorant"}, {"title": "SeownedDE x64 2025/3/29&#40;rei2&#41;", "link": "https://%75%6E%6B%6E%6F%77%6E%63%68%65%61%74%73.%6D%65/%66%6F%72%75%6D/team-fortress-2-a/694048-seownedde-x64-2025-3-29-rei2.html", "date": "2025-04-05 02:15:00", "forum": "Team Fortress 2"}, {"title": "GTA V Enhanced Unban Banned Steam Accounts", "link": "https://%75%6E%6B%6E%6F%77%6E%63%68%65%61%74%73.%6D%65/%66%6F%72%75%6D/grand-theft-auto-v/690287-gta-enhanced-unban-banned-steam-accounts.html", "date": "2025-04-05 02:11:00", "forum": "Grand Theft Auto V"}, {"title": "Valorunt v1 &#45; simple external AIM ASSIST", "link": "https://%75%6E%6B%6E%6F%77%6E%63%68%65%61%74%73.%6D%65/%66%6F%72%75%6D/valorant/692797-valorunt-v1-simple-external-aim-assist.html", "date": "2025-04-05 02:05:00", "forum": "Valorant"}, {"title": "All Mouse NoRecoil 1&#46;0 IS OUT &#91;Recoil Helpy&#93;&#91;Auto Config&#93;&#91;probably UD&#93;&#91;UNIVERSAL&#93;", "link": "https://%75%6E%6B%6E%6F%77%6E%63%68%65%61%74%73.%6D%65/%66%6F%72%75%6D/rainbow-six-siege/620039-mouse-norecoil-1-0-recoil-helpy-auto-config-probably-ud-universal.html", "date": "2025-04-05 01:55:00", "forum": "Rainbow Six Siege"}, {"title": "Redmatch 2 internal cheat &#40;imperium&#41;", "link": "https://%75%6E%6B%6E%6F%77%6E%63%68%65%61%74%73.%6D%65/%66%6F%72%75%6D/other-fps-games/688217-redmatch-2-internal-cheat-imperium.html", "date": "2025-04-05 01:48:00", "forum": "Other FPS Games"}, {"title": "Flags read properly, but bhop breaks inputs &#40;Shift/Ctrl/Mouse1&#41;", "link": "https://%75%6E%6B%6E%6F%77%6E%63%68%65%61%74%73.%6D%65/%66%6F%72%75%6D/counter-strike-2-a/695018-flags-read-properly-bhop-breaks-inputs-shift-ctrl-mouse1.html", "date": "2025-04-05 01:45:00", "forum": "Counter-Strike 2"}, {"title": "Zula Cheat DLL &#45; Flash &#40;leak&#41;", "link": "https://%75%6E%6B%6E%6F%77%6E%63%68%65%61%74%73.%6D%65/%66%6F%72%75%6D/other-fps-games/694958-zula-cheat-dll-flash-leak.html", "date": "2025-04-05 01:42:00", "forum": "Other FPS Games"}, {"title": "How to hide the mapped driver memory?", "link": "https://%75%6E%6B%6E%6F%77%6E%63%68%65%61%74%73.%6D%65/%66%6F%72%75%6D/anti-cheat-bypass/692617-hide-mapped-driver-memory.html", "date": "2025-04-05 01:37:00", "forum": "Anti-Cheat Bypass"}, {"title": "Making chams", "link": "https://%75%6E%6B%6E%6F%77%6E%63%68%65%61%74%73.%6D%65/%66%6F%72%75%6D/counter-strike-2-a/695030-chams.html", "date": "2025-04-05 01:37:00", "forum": "Counter-Strike 2"}, {"title": "ARMA Reforger Reversal, Structs and Offsets", "link": "https://%75%6E%6B%6E%6F%77%6E%63%68%65%61%74%73.%6D%65/%66%6F%72%75%6D/arma-3-a/499858-arma-reforger-reversal-structs-offsets.html", "date": "2025-04-05 01:29:00", "forum": "ARMA 3"}, {"title": "help define the enemy", "link": "https://%75%6E%6B%6E%6F%77%6E%63%68%65%61%74%73.%6D%65/%66%6F%72%75%6D/warface/694129-help-define-enemy.html", "date": "2025-04-05 01:19:00", "forum": "Warface"}, {"title": "STAR CITIZEN CHEAT ENGINE", "link": "https://%75%6E%6B%6E%6F%77%6E%63%68%65%61%74%73.%6D%65/%66%6F%72%75%6D/other-mmorpg-and-strategy/686927-star-citizen-cheat-engine.html", "date": "2025-04-05 01:16:00", "forum": "Other MMORPG and Strategy"}, {"title": "How can I find GWorld offset?", "link": "https://%75%6E%6B%6E%6F%77%6E%63%68%65%61%74%73.%6D%65/%66%6F%72%75%6D/all-points-bulletin/694190-gworld-offset.html", "date": "2025-04-05 01:14:00", "forum": "All Points Bulletin"}, {"title": "Do You Love Crypto?", "link": "https://%75%6E%6B%6E%6F%77%6E%63%68%65%61%74%73.%6D%65/%66%6F%72%75%6D/off-topic/673834-love-crypto.html", "date": "2025-04-05 01:11:00", "forum": "Off Topic"}, {"title": "custom avatar picture", "link": "https://%75%6E%6B%6E%6F%77%6E%63%68%65%61%74%73.%6D%65/%66%6F%72%75%6D/combat-master/684057-custom-avatar-picture.html", "date": "2025-04-05 01:06:00", "forum": "Combat Master"}, {"title": "Modest Menu Lua Scripting Megathread", "link": "https://%75%6E%6B%6E%6F%77%6E%63%68%65%61%74%73.%6D%65/%66%6F%72%75%6D/grand-theft-auto-v/463868-modest-menu-lua-scripting-megathread.html", "date": "2025-04-05 01:06:00", "forum": "Grand Theft Auto V"}, {"title": "AC Blocker RELEASE", "link": "https://%75%6E%6B%6E%6F%77%6E%63%68%65%61%74%73.%6D%65/%66%6F%72%75%6D/call-of-duty-black-ops-6-a/691938-ac-blocker-release.html", "date": "2025-04-05 01:05:00", "forum": "Call of Duty: Black Ops 6"}, {"title": "Most Advanced C&#35; Pixel Library &#40;3 ms&#41; &#45; Seeking Collaboration", "link": "https://%75%6E%6B%6E%6F%77%6E%63%68%65%61%74%73.%6D%65/%66%6F%72%75%6D/valorant/695005-advanced-pixel-library-3-ms-seeking-collaboration.html", "date": "2025-04-05 01:04:00", "forum": "Valorant"}, {"title": "Banned? Post here&#33; DATA COLLECTION THREAD", "link": "https://%75%6E%6B%6E%6F%77%6E%63%68%65%61%74%73.%6D%65/%66%6F%72%75%6D/grand-theft-auto-v/165200-banned-post-data-collection-thread.html", "date": "2025-04-05 00:55:00", "forum": "Grand Theft Auto V"}, {"title": "FiveM inf Money &#91;Works on some servers&#93;", "link": "https://%75%6E%6B%6E%6F%77%6E%63%68%65%61%74%73.%6D%65/%66%6F%72%75%6D/alternative-online-mods/691574-fivem-inf-money-servers.html", "date": "2025-04-05 00:50:00", "forum": "Alternative Online Mods"}, {"title": "Dead by Daylight &#45; ESP And Much More", "link": "https://%75%6E%6B%6E%6F%77%6E%63%68%65%61%74%73.%6D%65/%66%6F%72%75%6D/other-fps-games/625890-dead-daylight-esp.html", "date": "2025-04-05 00:47:00", "forum": "Other FPS Games"}, {"title": "YimMenuV2 E&E with money cheat &#40;No FSL&#41;", "link": "https://%75%6E%6B%6E%6F%77%6E%63%68%65%61%74%73.%6D%65/%66%6F%72%75%6D/grand-theft-auto-v/694886-yimmenuv2-money-cheat-fsl.html", "date": "2025-04-05 00:46:00", "forum": "Grand Theft Auto V"}, {"title": "Spring & Easter Banner Contest 2025 &#45; Winners&#33;", "link": "https://%75%6E%6B%6E%6F%77%6E%63%68%65%61%74%73.%6D%65/%66%6F%72%75%6D/information-and-announcements/694797-spring-easter-banner-contest-2025-winners.html", "date": "2025-04-05 00:45:00", "forum": "Information and Announcements"}, {"title": "DuneCore &#45; CS2 Best Triggerbot so far &#40;for legit players&#41;", "link": "https://%75%6E%6B%6E%6F%77%6E%63%68%65%61%74%73.%6D%65/%66%6F%72%75%6D/counter-strike-2-a/691168-dunecore-cs2-triggerbot-legit-players.html", "date": "2025-04-05 00:42:00", "forum": "Counter-Strike 2"}, {"title": "dropped esp rendering problem", "link": "https://%75%6E%6B%6E%6F%77%6E%63%68%65%61%74%73.%6D%65/%66%6F%72%75%6D/counter-strike-2-a/694909-dropped-esp-rendering.html", "date": "2025-04-05 00:42:00", "forum": "Counter-Strike 2"}, {"title": "The Speed Of Shared Memory Driver", "link": "https://%75%6E%6B%6E%6F%77%6E%63%68%65%61%74%73.%6D%65/%66%6F%72%75%6D/anti-cheat-bypass/694809-speed-shared-memory-driver.html", "date": "2025-04-05 00:36:00", "forum": "Anti-Cheat Bypass"}, {"title": "ENSD Ban reports", "link": "https://%75%6E%6B%6E%6F%77%6E%63%68%65%61%74%73.%6D%65/%66%6F%72%75%6D/elite-dangerous/435486-ensd-ban-reports.html", "date": "2025-04-05 00:35:00", "forum": "Elite: Dangerous"}, {"title": "Scedule I Blackjack winner", "link": "https://%75%6E%6B%6E%6F%77%6E%63%68%65%61%74%73.%6D%65/%66%6F%72%75%6D/other-games/694482-scedule-blackjack-winner.html", "date": "2025-04-05 00:33:00", "forum": "Other Games"}, {"title": "KM&#45;UM COMM using UM struct &#45; PoC", "link": "https://%75%6E%6B%6E%6F%77%6E%63%68%65%61%74%73.%6D%65/%66%6F%72%75%6D/anti-cheat-bypass/695038-km-um-comm-using-um-struct-poc.html", "date": "2025-04-05 00:32:00", "forum": "Anti-Cheat Bypass"}, {"title": "basic chams base", "link": "https://%75%6E%6B%6E%6F%77%6E%63%68%65%61%74%73.%6D%65/%66%6F%72%75%6D/call-of-duty-black-ops-6-a/688179-basic-chams-base.html", "date": "2025-04-05 00:29:00", "forum": "Call of Duty: Black Ops 6"}, {"title": "Fallout 76 BA2 Cheat Collection", "link": "https://%75%6E%6B%6E%6F%77%6E%63%68%65%61%74%73.%6D%65/%66%6F%72%75%6D/other-fps-games/519969-fallout-76-ba2-cheat-collection.html", "date": "2025-04-05 00:29:00", "forum": "Other FPS Games"}, {"title": "EMACLAB &#40;GamersClub&#41; Anticheat analysis", "link": "https://%75%6E%6B%6E%6F%77%6E%63%68%65%61%74%73.%6D%65/%66%6F%72%75%6D/anti-cheat-bypass/695037-emaclab-gamersclub-anticheat-analysis.html", "date": "2025-04-05 00:22:00", "forum": "Anti-Cheat Bypass"}, {"title": "Combat Master ESP&Aimbot Internal Auto Update", "link": "https://%75%6E%6B%6E%6F%77%6E%63%68%65%61%74%73.%6D%65/%66%6F%72%75%6D/combat-master/676427-combat-master-esp-aimbot-internal-auto-update.html", "date": "2025-04-05 00:20:00", "forum": "Combat Master"}, {"title": "Marvel Rivals Reversal, Structs and Offsets", "link": "https://%75%6E%6B%6E%6F%77%6E%63%68%65%61%74%73.%6D%65/%66%6F%72%75%6D/marvel-rivals/652967-marvel-rivals-reversal-structs-offsets.html", "date": "2025-04-05 00:19:00", "forum": "Marvel Rivals"}, {"title": "Is there any way to make an unlock all?", "link": "https://%75%6E%6B%6E%6F%77%6E%63%68%65%61%74%73.%6D%65/%66%6F%72%75%6D/combat-master/694753-unlock.html", "date": "2025-04-05 00:18:00", "forum": "Combat Master"}, {"title": "FiveM External Self Leak &#40;1604 to 3274&#41;", "link": "https://%75%6E%6B%6E%6F%77%6E%63%68%65%61%74%73.%6D%65/%66%6F%72%75%6D/alternative-online-mods/694182-fivem-external-self-leak-1604-3274-a.html", "date": "2025-04-05 00:09:00", "forum": "Alternative Online Mods"}, {"title": "Rust Reversal, Structs and Offsets", "link": "https://%75%6E%6B%6E%6F%77%6E%63%68%65%61%74%73.%6D%65/%66%6F%72%75%6D/rust/164256-rust-reversal-structs-offsets.html", "date": "2025-04-05 00:08:00", "forum": "Rust"}, {"title": "Yim Menu V2&#46;0", "link": "https://%75%6E%6B%6E%6F%77%6E%63%68%65%61%74%73.%6D%65/%66%6F%72%75%6D/grand-theft-auto-v/693751-yim-menu-v2-0-a.html", "date": "2025-04-05 00:06:00", "forum": "Grand Theft Auto V"}, {"title": "Call of Duty: Modern Warfare Reversal, Structs and Offsets", "link": "https://%75%6E%6B%6E%6F%77%6E%63%68%65%61%74%73.%6D%65/%66%6F%72%75%6D/call-of-duty-modern-warfare/384429-call-duty-modern-warfare-reversal-structs-offsets.html", "date": "2025-04-05 00:05:00", "forum": "Call of Duty: Modern Warfare"}, {"title": "AI Aimbot & Trigger Bot That Outperforms Internal and External Cheats \ud83d\udd25", "link": "https://%75%6E%6B%6E%6F%77%6E%63%68%65%61%74%73.%6D%65/%66%6F%72%75%6D/rainbow-six-siege/685011-ai-aimbot-trigger-bot-outperforms-internal-external-cheats.html", "date": "2025-04-04 23:56:00", "forum": "Rainbow Six Siege"}, {"title": "PVE Cheat", "link": "https://%75%6E%6B%6E%6F%77%6E%63%68%65%61%74%73.%6D%65/%66%6F%72%75%6D/escape-from-tarkov/656573-pve-cheat.html", "date": "2025-04-04 23:54:00", "forum": "Escape from Tarkov"}, {"title": "TarkovGUI &#124; PVE", "link": "https://%75%6E%6B%6E%6F%77%6E%63%68%65%61%74%73.%6D%65/%66%6F%72%75%6D/escape-from-tarkov/694944-tarkovgui-pve.html", "date": "2025-04-04 23:53:00", "forum": "Escape from Tarkov"}, {"title": "Nika Read Only", "link": "https://%75%6E%6B%6E%6F%77%6E%63%68%65%61%74%73.%6D%65/%66%6F%72%75%6D/apex-legends/640853-nika-read.html", "date": "2025-04-04 23:53:00", "forum": "Apex Legends"}, {"title": "Get truly FiveM version &#40;with modules&#41;", "link": "https://%75%6E%6B%6E%6F%77%6E%63%68%65%61%74%73.%6D%65/%66%6F%72%75%6D/alternative-online-mods/694937-truly-fivem-version-modules.html", "date": "2025-04-04 23:52:00", "forum": "Alternative Online Mods"}, {"title": "SoT Datamining &#43; Unreleased/Unused Assets", "link": "https://%75%6E%6B%6E%6F%77%6E%63%68%65%61%74%73.%6D%65/%66%6F%72%75%6D/sea-of-thieves/624262-sot-datamining-unreleased-unused-assets.html", "date": "2025-04-04 23:52:00", "forum": "Sea of Thieves"}]}