{"date": "2024-12-20", "hottest": [{"title": "Marvel Rivals aimbot and esp", "link": "https://%75%6E%6B%6E%6F%77%6E%63%68%65%61%74%73.%6D%65/%66%6F%72%75%6D/marvel-rivals/677440-marvel-rivals-aimbot-esp.html", "date": "2024-12-20 00:13:01", "forum": "marvel-rivals", "reply": "180"}, {"title": "Marvel Rivals Colorbot &#40;Arduino & No Arduino Support&#41;", "link": "https://%75%6E%6B%6E%6F%77%6E%63%68%65%61%74%73.%6D%65/%66%6F%72%75%6D/marvel-rivals/677136-marvel-rivals-colorbot-arduino-arduino-support.html", "date": "2024-12-20 00:13:01", "forum": "marvel-rivals", "reply": "49"}, {"title": "Marvel Rivals Python Instalocker", "link": "https://%75%6E%6B%6E%6F%77%6E%63%68%65%61%74%73.%6D%65/%66%6F%72%75%6D/marvel-rivals/677013-marvel-rivals-python-instalocker.html", "date": "2024-12-20 00:13:01", "forum": "marvel-rivals", "reply": "23"}, {"title": "Signed Spoofer By Microsoft&#40;EAC & BE&#41;  Early Christmas Present", "link": "https://%75%6E%6B%6E%6F%77%6E%63%68%65%61%74%73.%6D%65/%66%6F%72%75%6D/anti-cheat-bypass/677190-signed-spoofer-microsoft-eac-christmas.html", "date": "2024-12-20 00:13:01", "forum": "anti-cheat-bypass", "reply": "28"}, {"title": "100% UNDETECTED INJECTOR&#33; &#124; EAC/BE/VGK BYPASS&#33; \ud83d\udd25\ud83d\udd25", "link": "https://%75%6E%6B%6E%6F%77%6E%63%68%65%61%74%73.%6D%65/%66%6F%72%75%6D/anti-cheat-bypass/677613-100-undetected-injector-eac-vgk-bypass.html", "date": "2024-12-20 00:13:01", "forum": "anti-cheat-bypass", "reply": "26"}, {"title": "Strinova Internal &#40;Aimbot & ESP&#41;", "link": "https://%75%6E%6B%6E%6F%77%6E%63%68%65%61%74%73.%6D%65/%66%6F%72%75%6D/other-fps-games/677105-strinova-internal-aimbot-esp.html", "date": "2024-12-20 00:13:01", "forum": "other-fps-games", "reply": "23"}, {"title": "Combat Master &#124; Fully Featured Internal", "link": "https://%75%6E%6B%6E%6F%77%6E%63%68%65%61%74%73.%6D%65/%66%6F%72%75%6D/combat-master/677171-combat-master-featured-internal.html", "date": "2024-12-20 00:13:01", "forum": "combat-master", "reply": "40"}, {"title": "Simple Online Bypass", "link": "https://%75%6E%6B%6E%6F%77%6E%63%68%65%61%74%73.%6D%65/%66%6F%72%75%6D/grand-theft-auto-v/677320-simple-online-bypass.html", "date": "2024-12-20 00:13:01", "forum": "grand-theft-auto-v", "reply": "14"}, {"title": "EAC DMA cr3 shuffling fix", "link": "https://%75%6E%6B%6E%6F%77%6E%63%68%65%61%74%73.%6D%65/%66%6F%72%75%6D/anti-cheat-bypass/677322-eac-dma-cr3-shuffling-fix.html", "date": "2024-12-20 00:13:01", "forum": "anti-cheat-bypass", "reply": "28"}, {"title": "Yolov8 model for marvel rivals", "link": "https://%75%6E%6B%6E%6F%77%6E%63%68%65%61%74%73.%6D%65/%66%6F%72%75%6D/marvel-rivals/677707-yolov8-model-marvel-rivals.html", "date": "2024-12-20 00:13:01", "forum": "marvel-rivals", "reply": "14"}, {"title": "FACEIT DLL Hijack Exploit", "link": "https://%75%6E%6B%6E%6F%77%6E%63%68%65%61%74%73.%6D%65/%66%6F%72%75%6D/anti-cheat-bypass/677628-faceit-dll-hijack-exploit.html", "date": "2024-12-20 02:56:36", "forum": "anti-cheat-bypass", "reply": "12"}, {"title": "Genesis Bot V1&#46;1&#46;0 &#91;RL Ranked Bot&#93; with Source Code", "link": "https://%75%6E%6B%6E%6F%77%6E%63%68%65%61%74%73.%6D%65/%66%6F%72%75%6D/other-games/677130-genesis-bot-v1-1-0-rl-ranked-bot-source-code.html", "date": "2024-12-20 03:08:57", "forum": "other-games", "reply": "9"}, {"title": "YimMenu&#46;dll 1&#46;70 update", "link": "https://%75%6E%6B%6E%6F%77%6E%63%68%65%61%74%73.%6D%65/%66%6F%72%75%6D/grand-theft-auto-v/678007-yimmenu-dll-1-70-update.html", "date": "2024-12-20 20:57:17", "forum": "grand-theft-auto-v", "reply": "9"}], "files": [{"title": "marvel rivals sdk 19,12,2024", "link": "https://%75%6E%6B%6E%6F%77%6E%63%68%65%61%74%73.%6D%65/%66%6F%72%75%6D/downloads.php?do=file&id=47975", "date": "2024-12-20 00:13:01", "downloads": "36"}, {"title": "CE table for palworld", "link": "https://%75%6E%6B%6E%6F%77%6E%63%68%65%61%74%73.%6D%65/%66%6F%72%75%6D/downloads.php?do=file&id=47968", "date": "2024-12-20 00:13:01", "downloads": "4"}, {"title": "cfemen & gir489's Ready or Not hook v1&#46;6", "link": "https://%75%6E%6B%6E%6F%77%6E%63%68%65%61%74%73.%6D%65/%66%6F%72%75%6D/downloads.php?do=file&id=47965", "date": "2024-12-20 00:13:01", "downloads": "13"}, {"title": "FortniteGame&#45;33&#46;11&#45;CL&#45;38773622 SDK", "link": "https://%75%6E%6B%6E%6F%77%6E%63%68%65%61%74%73.%6D%65/%66%6F%72%75%6D/downloads.php?do=file&id=47961", "date": "2024-12-20 00:13:01", "downloads": "53"}, {"title": "MarvelRivals&#95;V1&#46;onnx", "link": "https://%75%6E%6B%6E%6F%77%6E%63%68%65%61%74%73.%6D%65/%66%6F%72%75%6D/downloads.php?do=file&id=47945", "date": "2024-12-20 00:13:01", "downloads": "199"}, {"title": "Pixel Gun 3D Cheat Engine Table V2", "link": "https://%75%6E%6B%6E%6F%77%6E%63%68%65%61%74%73.%6D%65/%66%6F%72%75%6D/downloads.php?do=file&id=47933", "date": "2024-12-20 00:13:01", "downloads": "163"}, {"title": "Auto Updating SAR cheat v1&#46;4", "link": "https://%75%6E%6B%6E%6F%77%6E%63%68%65%61%74%73.%6D%65/%66%6F%72%75%6D/downloads.php?do=file&id=47930", "date": "2024-12-20 00:13:01", "downloads": "70"}, {"title": "RLTool", "link": "https://%75%6E%6B%6E%6F%77%6E%63%68%65%61%74%73.%6D%65/%66%6F%72%75%6D/downloads.php?do=file&id=47929", "date": "2024-12-20 00:13:01", "downloads": "1"}, {"title": "Super Animal Royale Offset Finder v1&#46;3", "link": "https://%75%6E%6B%6E%6F%77%6E%63%68%65%61%74%73.%6D%65/%66%6F%72%75%6D/downloads.php?do=file&id=47928", "date": "2024-12-20 00:13:01", "downloads": "7"}, {"title": "RocketDumper", "link": "https://%75%6E%6B%6E%6F%77%6E%63%68%65%61%74%73.%6D%65/%66%6F%72%75%6D/downloads.php?do=file&id=47926", "date": "2024-12-20 00:13:01", "downloads": "7"}, {"title": "CS2External", "link": "https://%75%6E%6B%6E%6F%77%6E%63%68%65%61%74%73.%6D%65/%66%6F%72%75%6D/downloads.php?do=file&id=47952", "date": "2024-12-20 02:56:36", "downloads": "1"}, {"title": "UngTool 1&#46;3", "link": "https://%75%6E%6B%6E%6F%77%6E%63%68%65%61%74%73.%6D%65/%66%6F%72%75%6D/downloads.php?do=file&id=47944", "date": "2024-12-20 05:09:32", "downloads": "2"}, {"title": "johanna&#46;cc&#46;deadlock&#46;by&#46;pirolo december update", "link": "https://%75%6E%6B%6E%6F%77%6E%63%68%65%61%74%73.%6D%65/%66%6F%72%75%6D/downloads.php?do=file&id=47957", "date": "2024-12-20 06:26:44", "downloads": "2"}, {"title": "asc2&#46;zip", "link": "https://%75%6E%6B%6E%6F%77%6E%63%68%65%61%74%73.%6D%65/%66%6F%72%75%6D/downloads.php?do=file&id=47936", "date": "2024-12-20 06:37:04", "downloads": "1"}, {"title": "R6 Rage Cheat Source Code", "link": "https://%75%6E%6B%6E%6F%77%6E%63%68%65%61%74%73.%6D%65/%66%6F%72%75%6D/downloads.php?do=file&id=47937", "date": "2024-12-20 07:07:58", "downloads": "5"}, {"title": "razer rapid fire macros", "link": "https://%75%6E%6B%6E%6F%77%6E%63%68%65%61%74%73.%6D%65/%66%6F%72%75%6D/downloads.php?do=file&id=47964", "date": "2024-12-20 07:24:42", "downloads": "1"}, {"title": "5&#46;3&#46;2&#45;1442700&#43;&#43;depot&#95;marvel&#43;S0&#95;release&#45;Marvel", "link": "https://%75%6E%6B%6E%6F%77%6E%63%68%65%61%74%73.%6D%65/%66%6F%72%75%6D/downloads.php?do=file&id=47981", "date": "2024-12-20 07:29:46", "downloads": "1"}, {"title": "Menu SnowBreak", "link": "https://%75%6E%6B%6E%6F%77%6E%63%68%65%61%74%73.%6D%65/%66%6F%72%75%6D/downloads.php?do=file&id=47976", "date": "2024-12-20 07:29:46", "downloads": "2"}], "latest": [{"title": "Custom DLL for Running Conflict: Global Storm in Windowed", "link": "https://%75%6E%6B%6E%6F%77%6E%63%68%65%61%74%73.%6D%65/%66%6F%72%75%6D/other-mmorpg-and-strategy/678134-custom-dll-running-conflict-global-storm-windowed.html", "date": "2024-12-20 22:16:00", "forum": "Other MMORPG and Strategy"}, {"title": "Dump EAC your usermode", "link": "https://%75%6E%6B%6E%6F%77%6E%63%68%65%61%74%73.%6D%65/%66%6F%72%75%6D/anti-cheat-bypass/678130-dump-eac-usermode.html", "date": "2024-12-20 21:59:00", "forum": "Anti-Cheat Bypass"}, {"title": "Marvel Rivals Colorbot &#40;Arduino & No Arduino Support&#41;", "link": "https://%75%6E%6B%6E%6F%77%6E%63%68%65%61%74%73.%6D%65/%66%6F%72%75%6D/marvel-rivals/677136-marvel-rivals-colorbot-arduino-arduino-support.html", "date": "2024-12-20 21:58:00", "forum": "Marvel Rivals"}, {"title": "Farlight 84 Reversal, Structs and Offsets", "link": "https://%75%6E%6B%6E%6F%77%6E%63%68%65%61%74%73.%6D%65/%66%6F%72%75%6D/farlight-84-a/580566-farlight-84-reversal-structs-offsets.html", "date": "2024-12-20 21:28:00", "forum": "Farlight 84"}, {"title": "Paladins Reversal, Structs and Offsets", "link": "https://%75%6E%6B%6E%6F%77%6E%63%68%65%61%74%73.%6D%65/%66%6F%72%75%6D/paladins/217341-paladins-reversal-structs-offsets.html", "date": "2024-12-20 21:16:00", "forum": "Paladins"}, {"title": "Project Zomboid Cheat &#45; Valkur", "link": "https://%75%6E%6B%6E%6F%77%6E%63%68%65%61%74%73.%6D%65/%66%6F%72%75%6D/other-mmorpg-and-strategy/645408-project-zomboid-cheat-valkur.html", "date": "2024-12-20 21:07:00", "forum": "Other MMORPG and Strategy"}, {"title": "Ultimate Menu For YimMenu", "link": "https://%75%6E%6B%6E%6F%77%6E%63%68%65%61%74%73.%6D%65/%66%6F%72%75%6D/grand-theft-auto-v/597103-ultimate-menu-yimmenu.html", "date": "2024-12-20 20:48:00", "forum": "Grand Theft Auto V"}, {"title": "Modest Menu Lua Scripting Megathread", "link": "https://%75%6E%6B%6E%6F%77%6E%63%68%65%61%74%73.%6D%65/%66%6F%72%75%6D/grand-theft-auto-v/463868-modest-menu-lua-scripting-megathread.html", "date": "2024-12-20 20:39:00", "forum": "Grand Theft Auto V"}, {"title": "Controller Aim Assist On MNK", "link": "https://%75%6E%6B%6E%6F%77%6E%63%68%65%61%74%73.%6D%65/%66%6F%72%75%6D/call-of-duty-black-ops-6-a/678062-controller-aim-assist-mnk.html", "date": "2024-12-20 20:36:00", "forum": "Call of Duty: Black Ops 6"}, {"title": "Fix Vehicle", "link": "https://%75%6E%6B%6E%6F%77%6E%63%68%65%61%74%73.%6D%65/%66%6F%72%75%6D/alternative-online-mods/669238-fix-vehicle.html", "date": "2024-12-20 20:09:00", "forum": "Alternative Online Mods"}, {"title": "OW Color Triggerbot", "link": "https://%75%6E%6B%6E%6F%77%6E%63%68%65%61%74%73.%6D%65/%66%6F%72%75%6D/overwatch/677675-ow-color-triggerbot.html", "date": "2024-12-20 20:05:00", "forum": "Overwatch"}, {"title": "Which language would be better for making a external cheat?", "link": "https://%75%6E%6B%6E%6F%77%6E%63%68%65%61%74%73.%6D%65/%66%6F%72%75%6D/rust/678042-language-external-cheat.html", "date": "2024-12-20 20:02:00", "forum": "Rust"}, {"title": "maplestory world   player X  Y", "link": "https://%75%6E%6B%6E%6F%77%6E%63%68%65%61%74%73.%6D%65/%66%6F%72%75%6D/maple-story/678118-maplestory-world-player.html", "date": "2024-12-20 19:51:00", "forum": "Maple Story"}, {"title": "VALORANT MINION", "link": "https://%75%6E%6B%6E%6F%77%6E%63%68%65%61%74%73.%6D%65/%66%6F%72%75%6D/valorant/673460-valorant-minion.html", "date": "2024-12-20 19:38:00", "forum": "Valorant"}, {"title": "My Hero Ultra Rumble External", "link": "https://%75%6E%6B%6E%6F%77%6E%63%68%65%61%74%73.%6D%65/%66%6F%72%75%6D/other-games/670348-hero-ultra-rumble-external.html", "date": "2024-12-20 19:34:00", "forum": "Other Games"}, {"title": "c&#43;&#43; ColorBot Trig", "link": "https://%75%6E%6B%6E%6F%77%6E%63%68%65%61%74%73.%6D%65/%66%6F%72%75%6D/all-points-bulletin/671349-colorbot-trig.html", "date": "2024-12-20 19:25:00", "forum": "All Points Bulletin"}, {"title": "Vigor Internal Cheat", "link": "https://%75%6E%6B%6E%6F%77%6E%63%68%65%61%74%73.%6D%65/%66%6F%72%75%6D/other-fps-games/669274-vigor-internal-cheat.html", "date": "2024-12-20 18:59:00", "forum": "Other FPS Games"}, {"title": "War Thunder", "link": "https://%75%6E%6B%6E%6F%77%6E%63%68%65%61%74%73.%6D%65/%66%6F%72%75%6D/other-mmorpg-and-strategy/85949-war-thunder.html", "date": "2024-12-20 18:42:00", "forum": "Other MMORPG and Strategy"}, {"title": "DayZ&#45;InternalHack&#45;FullFeatures", "link": "https://%75%6E%6B%6E%6F%77%6E%63%68%65%61%74%73.%6D%65/%66%6F%72%75%6D/dayz-sa/677192-dayz-internalhack-fullfeatures.html", "date": "2024-12-20 17:50:00", "forum": "DayZ SA"}, {"title": "ENSD v18", "link": "https://%75%6E%6B%6E%6F%77%6E%63%68%65%61%74%73.%6D%65/%66%6F%72%75%6D/elite-dangerous/658785-ensd-v18.html", "date": "2024-12-20 17:46:00", "forum": "Elite: Dangerous"}, {"title": "Spankerfield &#45; Beautiful ESP / Code base / Clean screenshots", "link": "https://%75%6E%6B%6E%6F%77%6E%63%68%65%61%74%73.%6D%65/%66%6F%72%75%6D/battlefield-4-a/493695-spankerfield-beautiful-esp-code-base-clean-screenshots.html", "date": "2024-12-20 17:40:00", "forum": "Battlefield 4"}, {"title": "ZeroHVCI &#45; Defeating HVCI without admin privileges or a kernel drivers", "link": "https://%75%6E%6B%6E%6F%77%6E%63%68%65%61%74%73.%6D%65/%66%6F%72%75%6D/anti-cheat-bypass/650057-zerohvci-defeating-hvci-admin-privileges-kernel-drivers.html", "date": "2024-12-20 17:28:00", "forum": "Anti-Cheat Bypass"}, {"title": "No Recoil", "link": "https://%75%6E%6B%6E%6F%77%6E%63%68%65%61%74%73.%6D%65/%66%6F%72%75%6D/rainbow-six-siege/675931-recoil.html", "date": "2024-12-20 17:00:00", "forum": "Rainbow Six Siege"}, {"title": "BincoHaX for 1&#46;70 &#91;External&#93;", "link": "https://%75%6E%6B%6E%6F%77%6E%63%68%65%61%74%73.%6D%65/%66%6F%72%75%6D/grand-theft-auto-v/250308-bincohax-1-70-external.html", "date": "2024-12-20 16:13:00", "forum": "Grand Theft Auto V"}, {"title": "War Thunder offset dumper source", "link": "https://%75%6E%6B%6E%6F%77%6E%63%68%65%61%74%73.%6D%65/%66%6F%72%75%6D/other-mmorpg-and-strategy/667525-war-thunder-offset-dumper-source.html", "date": "2024-12-20 16:09:00", "forum": "Other MMORPG and Strategy"}, {"title": "Dark and Darker &#91;Aimbot,Esp,Misc&#93;", "link": "https://%75%6E%6B%6E%6F%77%6E%63%68%65%61%74%73.%6D%65/%66%6F%72%75%6D/other-fps-games/618062-dark-darker-aimbot-esp-misc.html", "date": "2024-12-20 15:33:00", "forum": "Other FPS Games"}, {"title": "Josh's Aim Assist V1", "link": "https://%75%6E%6B%6E%6F%77%6E%63%68%65%61%74%73.%6D%65/%66%6F%72%75%6D/call-of-duty-black-ops-6-a/670254-joshs-aim-assist-v1.html", "date": "2024-12-20 15:56:00", "forum": "Call of Duty: Black Ops 6"}, {"title": "ARK: Survival Ascended Reversal, Structs and Offsets", "link": "https://%75%6E%6B%6E%6F%77%6E%63%68%65%61%74%73.%6D%65/%66%6F%72%75%6D/other-fps-games/608333-ark-survival-ascended-reversal-structs-offsets.html", "date": "2024-12-20 14:01:00", "forum": "Other FPS Games"}, {"title": "Hunt Showdown Internal or External", "link": "https://%75%6E%6B%6E%6F%77%6E%63%68%65%61%74%73.%6D%65/%66%6F%72%75%6D/other-fps-games/677824-hunt-showdown-internal-external.html", "date": "2024-12-20 13:57:00", "forum": "Other FPS Games"}, {"title": "Fast Valorant Triggerbot", "link": "https://%75%6E%6B%6E%6F%77%6E%63%68%65%61%74%73.%6D%65/%66%6F%72%75%6D/valorant/669778-fast-valorant-triggerbot.html", "date": "2024-12-20 13:44:00", "forum": "Valorant"}, {"title": "Dead by Daylight", "link": "https://%75%6E%6B%6E%6F%77%6E%63%68%65%61%74%73.%6D%65/%66%6F%72%75%6D/other-fps-games/178856-dead-daylight.html", "date": "2024-12-20 13:20:00", "forum": "Other FPS Games"}, {"title": "External visibility check", "link": "https://%75%6E%6B%6E%6F%77%6E%63%68%65%61%74%73.%6D%65/%66%6F%72%75%6D/counter-strike-2-a/591548-external-visibility-check.html", "date": "2024-12-20 13:03:00", "forum": "Counter-Strike 2"}, {"title": "BO6 DMA ESP", "link": "https://%75%6E%6B%6E%6F%77%6E%63%68%65%61%74%73.%6D%65/%66%6F%72%75%6D/call-of-duty-black-ops-6-a/670998-bo6-dma-esp.html", "date": "2024-12-20 13:02:00", "forum": "Call of Duty: Black Ops 6"}, {"title": "Genesis Bot V1&#46;1&#46;0 &#91;RL Ranked Bot&#93; with Source Code", "link": "https://%75%6E%6B%6E%6F%77%6E%63%68%65%61%74%73.%6D%65/%66%6F%72%75%6D/other-games/677130-genesis-bot-v1-1-0-rl-ranked-bot-source-code.html", "date": "2024-12-20 12:28:00", "forum": "Other Games"}, {"title": "Signed Spoofer By Microsoft&#40;EAC & BE&#41;  Early Christmas Present", "link": "https://%75%6E%6B%6E%6F%77%6E%63%68%65%61%74%73.%6D%65/%66%6F%72%75%6D/anti-cheat-bypass/677190-signed-spoofer-microsoft-eac-christmas.html", "date": "2024-12-20 12:27:00", "forum": "Anti-Cheat Bypass"}, {"title": "Osussist v3 MultiHack for osu&#33;", "link": "https://%75%6E%6B%6E%6F%77%6E%63%68%65%61%74%73.%6D%65/%66%6F%72%75%6D/other-games/671577-osussist-v3-multihack-osu.html", "date": "2024-12-20 12:04:00", "forum": "Other Games"}, {"title": "BSOD When calling GetModuleBase", "link": "https://%75%6E%6B%6E%6F%77%6E%63%68%65%61%74%73.%6D%65/%66%6F%72%75%6D/general-programming-and-reversing/678000-bsod-calling-getmodulebase.html", "date": "2024-12-20 10:49:00", "forum": "General Programming and Reversing"}, {"title": "How do I find SetValue function in IDA?", "link": "https://%75%6E%6B%6E%6F%77%6E%63%68%65%61%74%73.%6D%65/%66%6F%72%75%6D/garry-s-mod/677635-setvalue-function-ida.html", "date": "2024-12-20 10:49:00", "forum": "Garry's Mod"}, {"title": "Driver advice", "link": "https://%75%6E%6B%6E%6F%77%6E%63%68%65%61%74%73.%6D%65/%66%6F%72%75%6D/anti-cheat-bypass/678063-driver-advice.html", "date": "2024-12-20 10:40:00", "forum": "Anti-Cheat Bypass"}, {"title": "Centralized Bot Lobby Starter Python Script", "link": "https://%75%6E%6B%6E%6F%77%6E%63%68%65%61%74%73.%6D%65/%66%6F%72%75%6D/call-of-duty-black-ops-6-a/672158-centralized-bot-lobby-starter-python-script.html", "date": "2024-12-20 10:30:00", "forum": "Call of Duty: Black Ops 6"}, {"title": "how to give xp through friend code", "link": "https://%75%6E%6B%6E%6F%77%6E%63%68%65%61%74%73.%6D%65/%66%6F%72%75%6D/helldivers-2-a/665747-xp-friend-code.html", "date": "2024-12-20 09:35:00", "forum": "HELLDIVERS 2"}, {"title": "Shot Around Walls", "link": "https://%75%6E%6B%6E%6F%77%6E%63%68%65%61%74%73.%6D%65/%66%6F%72%75%6D/escape-from-tarkov/678067-shot-walls.html", "date": "2024-12-20 09:31:00", "forum": "Escape from Tarkov"}, {"title": "W11 24H2 data ptr driver communication method", "link": "https://%75%6E%6B%6E%6F%77%6E%63%68%65%61%74%73.%6D%65/%66%6F%72%75%6D/anti-cheat-bypass/652498-w11-24h2-data-ptr-driver-communication-method.html", "date": "2024-12-20 09:26:00", "forum": "Anti-Cheat Bypass"}, {"title": "rig slot machines", "link": "https://%75%6E%6B%6E%6F%77%6E%63%68%65%61%74%73.%6D%65/%66%6F%72%75%6D/grand-theft-auto-v/677715-rig-slot-machines.html", "date": "2024-12-20 09:22:00", "forum": "Grand Theft Auto V"}, {"title": "Load Custom RPFs With YimMenu", "link": "https://%75%6E%6B%6E%6F%77%6E%63%68%65%61%74%73.%6D%65/%66%6F%72%75%6D/grand-theft-auto-v/677966-load-custom-rpfs-yimmenu.html", "date": "2024-12-20 09:20:00", "forum": "Grand Theft Auto V"}, {"title": "Webs PVE Menu v3 &#40;Edit&#41;", "link": "https://%75%6E%6B%6E%6F%77%6E%63%68%65%61%74%73.%6D%65/%66%6F%72%75%6D/escape-from-tarkov/651661-webs-pve-menu-v3-edit.html", "date": "2024-12-20 09:12:00", "forum": "Escape from Tarkov"}, {"title": "BotOps Hub &#40;bot lobby tool, no VM required&#41;", "link": "https://%75%6E%6B%6E%6F%77%6E%63%68%65%61%74%73.%6D%65/%66%6F%72%75%6D/call-of-duty-black-ops-6-a/674129-botops-hub-bot-lobby-tool-vm-required.html", "date": "2024-12-20 08:37:00", "forum": "Call of Duty: Black Ops 6"}, {"title": "EAC DMA cr3 shuffling fix", "link": "https://%75%6E%6B%6E%6F%77%6E%63%68%65%61%74%73.%6D%65/%66%6F%72%75%6D/anti-cheat-bypass/677322-eac-dma-cr3-shuffling-fix.html", "date": "2024-12-20 08:34:00", "forum": "Anti-Cheat Bypass"}, {"title": "DayZ Reversal, Structs and Offsets", "link": "https://%75%6E%6B%6E%6F%77%6E%63%68%65%61%74%73.%6D%65/%66%6F%72%75%6D/dayz-sa/104269-dayz-reversal-structs-offsets.html", "date": "2024-12-20 08:22:00", "forum": "DayZ SA"}, {"title": "How to calculate multipoint for bone/hitbox", "link": "https://%75%6E%6B%6E%6F%77%6E%63%68%65%61%74%73.%6D%65/%66%6F%72%75%6D/counter-strike-2-a/678058-calculate-multipoint-bone-hitbox.html", "date": "2024-12-20 08:05:00", "forum": "Counter-Strike 2"}, {"title": "My Hero Ultra Rumble Cheat Table", "link": "https://%75%6E%6B%6E%6F%77%6E%63%68%65%61%74%73.%6D%65/%66%6F%72%75%6D/other-games/604426-hero-ultra-rumble-cheat-table.html", "date": "2024-12-20 07:50:00", "forum": "Other Games"}, {"title": "Is Rewasd Safe now ?", "link": "https://%75%6E%6B%6E%6F%77%6E%63%68%65%61%74%73.%6D%65/%66%6F%72%75%6D/apex-legends/677879-rewasd-safe.html", "date": "2024-12-20 07:48:00", "forum": "Apex Legends"}, {"title": "Rocket League &#45; Dumper &#40;x64&#41;", "link": "https://%75%6E%6B%6E%6F%77%6E%63%68%65%61%74%73.%6D%65/%66%6F%72%75%6D/other-fps-games/402519-rocket-league-dumper-x64.html", "date": "2024-12-20 07:38:00", "forum": "Other FPS Games"}, {"title": "CS2 External Cheat", "link": "https://%75%6E%6B%6E%6F%77%6E%63%68%65%61%74%73.%6D%65/%66%6F%72%75%6D/counter-strike-2-a/660877-cs2-external-cheat.html", "date": "2024-12-20 07:35:00", "forum": "Counter-Strike 2"}, {"title": "Bodycam Internal &#40;ESP, Godmode, Rapid Fire, No Recoil&#46;&#46;&#46;&#41;", "link": "https://%75%6E%6B%6E%6F%77%6E%63%68%65%61%74%73.%6D%65/%66%6F%72%75%6D/other-fps-games/661430-bodycam-internal-esp-godmode-rapid-fire-recoil.html", "date": "2024-12-20 07:32:00", "forum": "Other FPS Games"}, {"title": "Menu SnoBreak", "link": "https://%75%6E%6B%6E%6F%77%6E%63%68%65%61%74%73.%6D%65/%66%6F%72%75%6D/other-mmorpg-and-strategy/620147-menu-snobreak.html", "date": "2024-12-20 07:26:00", "forum": "Other MMORPG and Strategy"}, {"title": "seo64", "link": "https://%75%6E%6B%6E%6F%77%6E%63%68%65%61%74%73.%6D%65/%66%6F%72%75%6D/team-fortress-2-a/662767-seo64.html", "date": "2024-12-20 07:25:00", "forum": "Team Fortress 2"}, {"title": "Razer macros: rapid fire", "link": "https://%75%6E%6B%6E%6F%77%6E%63%68%65%61%74%73.%6D%65/%66%6F%72%75%6D/call-of-duty-black-ops-6-a/677911-razer-macros-rapid-fire.html", "date": "2024-12-20 07:17:00", "forum": "Call of Duty: Black Ops 6"}, {"title": "Host&#95;IsSecureServerAllowed sig", "link": "https://%75%6E%6B%6E%6F%77%6E%63%68%65%61%74%73.%6D%65/%66%6F%72%75%6D/team-fortress-2-a/677806-host_issecureserverallowed-sig.html", "date": "2024-12-20 07:15:00", "forum": "Team Fortress 2"}, {"title": "Atom V4 Source Code", "link": "https://%75%6E%6B%6E%6F%77%6E%63%68%65%61%74%73.%6D%65/%66%6F%72%75%6D/crysis/677859-atom-v4-source-code.html", "date": "2024-12-20 07:15:00", "forum": "Crysis"}, {"title": "Arduino FirmWare UD", "link": "https://%75%6E%6B%6E%6F%77%6E%63%68%65%61%74%73.%6D%65/%66%6F%72%75%6D/valorant/676366-arduino-firmware-ud.html", "date": "2024-12-20 07:13:00", "forum": "Valorant"}, {"title": "Fivem external anti headshot", "link": "https://%75%6E%6B%6E%6F%77%6E%63%68%65%61%74%73.%6D%65/%66%6F%72%75%6D/alternative-online-mods/677656-fivem-external-anti-headshot.html", "date": "2024-12-20 07:03:00", "forum": "Alternative Online Mods"}, {"title": "Basic Kernel Driver Source &#91;Foundational&#93;", "link": "https://%75%6E%6B%6E%6F%77%6E%63%68%65%61%74%73.%6D%65/%66%6F%72%75%6D/anti-cheat-bypass/677856-basic-kernel-driver-source-foundational.html", "date": "2024-12-20 06:55:00", "forum": "Anti-Cheat Bypass"}, {"title": "Auto IDA64 script python BaseNetworkable", "link": "https://%75%6E%6B%6E%6F%77%6E%63%68%65%61%74%73.%6D%65/%66%6F%72%75%6D/rust/677705-auto-ida64-script-python-basenetworkable.html", "date": "2024-12-20 06:54:00", "forum": "Rust"}, {"title": "MacOS Rust External ESP w/ Bypass", "link": "https://%75%6E%6B%6E%6F%77%6E%63%68%65%61%74%73.%6D%65/%66%6F%72%75%6D/rust/676320-macos-rust-external-esp-bypass.html", "date": "2024-12-20 06:53:00", "forum": "Rust"}, {"title": "RainbowSix Internal Rage Source", "link": "https://%75%6E%6B%6E%6F%77%6E%63%68%65%61%74%73.%6D%65/%66%6F%72%75%6D/rainbow-six-siege/677592-rainbowsix-internal-rage-source.html", "date": "2024-12-20 06:52:00", "forum": "Rainbow Six Siege"}, {"title": "D3D11RenderThread Crash", "link": "https://%75%6E%6B%6E%6F%77%6E%63%68%65%61%74%73.%6D%65/%66%6F%72%75%6D/counter-strike-2-a/678052-d3d11renderthread-crash.html", "date": "2024-12-20 06:46:00", "forum": "Counter-Strike 2"}, {"title": "Assassin's Creed 2 Memory Modifier", "link": "https://%75%6E%6B%6E%6F%77%6E%63%68%65%61%74%73.%6D%65/%66%6F%72%75%6D/other-single-player-games/677546-assassins-creed-2-memory-modifier.html", "date": "2024-12-20 06:36:00", "forum": "Other Single Player Games"}, {"title": "Updated chams", "link": "https://%75%6E%6B%6E%6F%77%6E%63%68%65%61%74%73.%6D%65/%66%6F%72%75%6D/rainbow-six-siege/642477-updated-chams.html", "date": "2024-12-20 06:33:00", "forum": "Rainbow Six Siege"}, {"title": "Triggerbot won't detect the head color outline", "link": "https://%75%6E%6B%6E%6F%77%6E%63%68%65%61%74%73.%6D%65/%66%6F%72%75%6D/valorant/678049-triggerbot-wont-detect-head-color-outline.html", "date": "2024-12-20 06:20:00", "forum": "Valorant"}, {"title": "Cold War ESP", "link": "https://%75%6E%6B%6E%6F%77%6E%63%68%65%61%74%73.%6D%65/%66%6F%72%75%6D/call-of-duty-black-ops-cold-war/677838-cold-war-esp.html", "date": "2024-12-20 05:38:00", "forum": "Call of Duty: Black Ops Cold War"}, {"title": "Phasmophobia cheat hub", "link": "https://%75%6E%6B%6E%6F%77%6E%63%68%65%61%74%73.%6D%65/%66%6F%72%75%6D/phasmophobia/677606-phasmophobia-cheat-hub.html", "date": "2024-12-20 05:38:00", "forum": "Phasmophobia"}, {"title": "Aim Assist in pure C", "link": "https://%75%6E%6B%6E%6F%77%6E%63%68%65%61%74%73.%6D%65/%66%6F%72%75%6D/valorant/675938-aim-assist-pure.html", "date": "2024-12-20 05:38:00", "forum": "Valorant"}, {"title": "who can help please", "link": "https://%75%6E%6B%6E%6F%77%6E%63%68%65%61%74%73.%6D%65/%66%6F%72%75%6D/team-fortress-2-a/677144-help-please.html", "date": "2024-12-20 05:34:00", "forum": "Team Fortress 2"}, {"title": "Precision The Division 1 Cheat &#91;Silent Aim, Magic Bullets, etc&#46;&#46;&#93;", "link": "https://%75%6E%6B%6E%6F%77%6E%63%68%65%61%74%73.%6D%65/%66%6F%72%75%6D/tom-clancy-s-the-division/673526-precision-division-1-cheat-silent-aim-magic-bullets-etc.html", "date": "2024-12-20 05:34:00", "forum": "Tom Clancy's The Division"}, {"title": "XianYuMods", "link": "https://%75%6E%6B%6E%6F%77%6E%63%68%65%61%74%73.%6D%65/%66%6F%72%75%6D/payday-3-a/661692-xianyumods.html", "date": "2024-12-20 05:34:00", "forum": "Payday 3"}, {"title": "New to this world", "link": "https://%75%6E%6B%6E%6F%77%6E%63%68%65%61%74%73.%6D%65/%66%6F%72%75%6D/forum-general/677989-world.html", "date": "2024-12-20 05:34:00", "forum": "Forum General"}, {"title": "Deadlock External", "link": "https://%75%6E%6B%6E%6F%77%6E%63%68%65%61%74%73.%6D%65/%66%6F%72%75%6D/deadlock/663070-deadlock-external.html", "date": "2024-12-20 05:31:00", "forum": "Deadlock"}, {"title": "Rust Lua Release", "link": "https://%75%6E%6B%6E%6F%77%6E%63%68%65%61%74%73.%6D%65/%66%6F%72%75%6D/rust/677056-rust-lua-release.html", "date": "2024-12-20 05:28:00", "forum": "Rust"}, {"title": "BO6 Enhanced Color Aim AHK GUI", "link": "https://%75%6E%6B%6E%6F%77%6E%63%68%65%61%74%73.%6D%65/%66%6F%72%75%6D/call-of-duty-black-ops-6-a/671390-bo6-enhanced-color-aim-ahk-gui.html", "date": "2024-12-20 05:25:00", "forum": "Call of Duty: Black Ops 6"}, {"title": "Trouble disabling mouse input when imgui menu is open", "link": "https://%75%6E%6B%6E%6F%77%6E%63%68%65%61%74%73.%6D%65/%66%6F%72%75%6D/counter-strike-2-a/677890-trouble-disabling-mouse-input-imgui-menu.html", "date": "2024-12-20 05:05:00", "forum": "Counter-Strike 2"}, {"title": "UngTool 1&#46;0 &#45; 1&#46;68", "link": "https://%75%6E%6B%6E%6F%77%6E%63%68%65%61%74%73.%6D%65/%66%6F%72%75%6D/grand-theft-auto-v/639045-ungtool-1-0-1-68-a.html", "date": "2024-12-20 05:03:00", "forum": "Grand Theft Auto V"}, {"title": "Internal Triggerbot Inaccuracy", "link": "https://%75%6E%6B%6E%6F%77%6E%63%68%65%61%74%73.%6D%65/%66%6F%72%75%6D/counter-strike-2-a/678005-internal-triggerbot-inaccuracy.html", "date": "2024-12-20 05:00:00", "forum": "Counter-Strike 2"}, {"title": "Arena Breakout Infinite Internal Hack", "link": "https://%75%6E%6B%6E%6F%77%6E%63%68%65%61%74%73.%6D%65/%66%6F%72%75%6D/other-fps-games/641795-arena-breakout-infinite-internal-hack.html", "date": "2024-12-20 04:41:00", "forum": "Other FPS Games"}, {"title": "Nika Read Only", "link": "https://%75%6E%6B%6E%6F%77%6E%63%68%65%61%74%73.%6D%65/%66%6F%72%75%6D/apex-legends/640853-nika-read.html", "date": "2024-12-20 04:31:00", "forum": "Apex Legends"}, {"title": "Odin v4 For Windows 11 24H2/23H2", "link": "https://%75%6E%6B%6E%6F%77%6E%63%68%65%61%74%73.%6D%65/%66%6F%72%75%6D/paladins/670695-odin-v4-windows-11-24h2-23h2.html", "date": "2024-12-20 04:18:00", "forum": "Paladins"}, {"title": "Free Cheat Chams", "link": "https://%75%6E%6B%6E%6F%77%6E%63%68%65%61%74%73.%6D%65/%66%6F%72%75%6D/rainbow-six-siege/677967-free-cheat-chams.html", "date": "2024-12-20 04:17:00", "forum": "Rainbow Six Siege"}, {"title": "Yolov8 model for marvel rivals", "link": "https://%75%6E%6B%6E%6F%77%6E%63%68%65%61%74%73.%6D%65/%66%6F%72%75%6D/marvel-rivals/677707-yolov8-model-marvel-rivals.html", "date": "2024-12-20 03:56:00", "forum": "Marvel Rivals"}, {"title": "Skin Changer", "link": "https://%75%6E%6B%6E%6F%77%6E%63%68%65%61%74%73.%6D%65/%66%6F%72%75%6D/counter-strike-2-a/671590-skin-changer.html", "date": "2024-12-20 03:49:00", "forum": "Counter-Strike 2"}, {"title": "GTA:SA/SAMP cheat menu mod", "link": "https://%75%6E%6B%6E%6F%77%6E%63%68%65%61%74%73.%6D%65/%66%6F%72%75%6D/other-single-player-games/677373-gta-sa-samp-cheat-menu-mod.html", "date": "2024-12-20 03:49:00", "forum": "Other Single Player Games"}, {"title": "Certeficates leak :&#41; Apple and etc&#46;", "link": "https://%75%6E%6B%6E%6F%77%6E%63%68%65%61%74%73.%6D%65/%66%6F%72%75%6D/anti-cheat-bypass/678013-certeficates-leak-apple-etc.html", "date": "2024-12-20 03:49:00", "forum": "Anti-Cheat Bypass"}, {"title": "BugCheck 24H2", "link": "https://%75%6E%6B%6E%6F%77%6E%63%68%65%61%74%73.%6D%65/%66%6F%72%75%6D/general-programming-and-reversing/678010-bugcheck-24h2.html", "date": "2024-12-20 03:43:00", "forum": "General Programming and Reversing"}, {"title": "SCS2 &#45; Semi&#45;External Mod for Counter&#45;Strike 2", "link": "https://%75%6E%6B%6E%6F%77%6E%63%68%65%61%74%73.%6D%65/%66%6F%72%75%6D/counter-strike-2-releases/651580-scs2-semi-external-mod-counter-strike-2-a.html", "date": "2024-12-20 03:40:00", "forum": "Counter-Strike 2 Releases"}, {"title": "cfemen & gir489's Ready or Not hook v1&#46;0", "link": "https://%75%6E%6B%6E%6F%77%6E%63%68%65%61%74%73.%6D%65/%66%6F%72%75%6D/other-fps-games/632144-cfemen-gir489s-ready-hook-v1-0-a.html", "date": "2024-12-20 03:26:00", "forum": "Other FPS Games"}, {"title": "SmmInfect &#45; Smm Backdoor", "link": "https://%75%6E%6B%6E%6F%77%6E%63%68%65%61%74%73.%6D%65/%66%6F%72%75%6D/anti-cheat-bypass/664482-smminfect-smm-backdoor.html", "date": "2024-12-20 03:32:00", "forum": "Anti-Cheat Bypass"}, {"title": "How is this guy playing with StaffBesting for 2 months without ban?", "link": "https://%75%6E%6B%6E%6F%77%6E%63%68%65%61%74%73.%6D%65/%66%6F%72%75%6D/valorant/677746-guy-playing-staffbesting-2-months-ban.html", "date": "2024-12-20 03:24:00", "forum": "Valorant"}, {"title": "Rigel Updated ow2", "link": "https://%75%6E%6B%6E%6F%77%6E%63%68%65%61%74%73.%6D%65/%66%6F%72%75%6D/overwatch/657856-rigel-updated-ow2.html", "date": "2024-12-20 03:22:00", "forum": "Overwatch"}, {"title": "Overwatch 2 Reversal, Structs and Offsets", "link": "https://%75%6E%6B%6E%6F%77%6E%63%68%65%61%74%73.%6D%65/%66%6F%72%75%6D/overwatch/516727-overwatch-2-reversal-structs-offsets.html", "date": "2024-12-20 03:20:00", "forum": "Overwatch"}, {"title": "YimMenu&#46;dll 1&#46;70 update", "link": "https://%75%6E%6B%6E%6F%77%6E%63%68%65%61%74%73.%6D%65/%66%6F%72%75%6D/grand-theft-auto-v/678007-yimmenu-dll-1-70-update.html", "date": "2024-12-20 03:20:00", "forum": "Grand Theft Auto V"}, {"title": "&#124; Dota 2 &#124; Nest of Throns: skills without cooldowns &#124; EXTERNAL &#124;", "link": "https://%75%6E%6B%6E%6F%77%6E%63%68%65%61%74%73.%6D%65/%66%6F%72%75%6D/other-mmorpg-and-strategy/677527-dota-2-nest-throns-skills-cooldowns-external.html", "date": "2024-12-20 02:52:00", "forum": "Other MMORPG and Strategy"}, {"title": "CS2External Aim/Esp/Misc", "link": "https://%75%6E%6B%6E%6F%77%6E%63%68%65%61%74%73.%6D%65/%66%6F%72%75%6D/counter-strike-2-releases/673859-cs2external-aim-esp-misc.html", "date": "2024-12-20 02:51:00", "forum": "Counter-Strike 2 Releases"}, {"title": "head bone position", "link": "https://%75%6E%6B%6E%6F%77%6E%63%68%65%61%74%73.%6D%65/%66%6F%72%75%6D/call-of-duty-black-ops-6-a/677595-head-bone-position.html", "date": "2024-12-20 02:46:00", "forum": "Call of Duty: Black Ops 6"}, {"title": "Globals and Locals&#40;no discussion, read page 1&#41;", "link": "https://%75%6E%6B%6E%6F%77%6E%63%68%65%61%74%73.%6D%65/%66%6F%72%75%6D/grand-theft-auto-v/500059-globals-locals-discussion-read-page-1-a.html", "date": "2024-12-20 02:42:00", "forum": "Grand Theft Auto V"}, {"title": "GamerFun AI Menu: All mouse Aimbot, Triggerbot & Recoil Control Using LGUB Drivers", "link": "https://%75%6E%6B%6E%6F%77%6E%63%68%65%61%74%73.%6D%65/%66%6F%72%75%6D/rainbow-six-siege/671029-gamerfun-ai-menu-mouse-aimbot-triggerbot-recoil-control-using-lgub-drivers.html", "date": "2024-12-20 02:36:00", "forum": "Rainbow Six Siege"}, {"title": "Running multiple instances of valorant", "link": "https://%75%6E%6B%6E%6F%77%6E%63%68%65%61%74%73.%6D%65/%66%6F%72%75%6D/valorant/660503-running-multiple-instances-valorant.html", "date": "2024-12-20 02:34:00", "forum": "Valorant"}, {"title": "RLMarlbot", "link": "https://%75%6E%6B%6E%6F%77%6E%63%68%65%61%74%73.%6D%65/%66%6F%72%75%6D/other-games/633336-rlmarlbot.html", "date": "2024-12-20 02:33:00", "forum": "Other Games"}, {"title": "YimMenu &#91;1&#46;69 &#45; b3351&#93;", "link": "https://%75%6E%6B%6E%6F%77%6E%63%68%65%61%74%73.%6D%65/%66%6F%72%75%6D/grand-theft-auto-v/476972-yimmenu-1-69-b3351.html", "date": "2024-12-20 02:33:00", "forum": "Grand Theft Auto V"}, {"title": "Counter&#45;Strike 2 Reversal, Structs and Offsets", "link": "https://%75%6E%6B%6E%6F%77%6E%63%68%65%61%74%73.%6D%65/%66%6F%72%75%6D/counter-strike-2-a/576077-counter-strike-2-reversal-structs-offsets.html", "date": "2024-12-20 02:29:00", "forum": "Counter-Strike 2"}, {"title": "Kernel Driver EAC", "link": "https://%75%6E%6B%6E%6F%77%6E%63%68%65%61%74%73.%6D%65/%66%6F%72%75%6D/rust/678003-kernel-driver-eac.html", "date": "2024-12-20 02:29:00", "forum": "Rust"}, {"title": "BO6 Windows Edition Uninstalls Itself", "link": "https://%75%6E%6B%6E%6F%77%6E%63%68%65%61%74%73.%6D%65/%66%6F%72%75%6D/call-of-duty-black-ops-6-a/677933-bo6-windows-edition-uninstalls.html", "date": "2024-12-20 02:29:00", "forum": "Call of Duty: Black Ops 6"}, {"title": "Helldivers 2&#45;&#45;AHK Stratagems", "link": "https://%75%6E%6B%6E%6F%77%6E%63%68%65%61%74%73.%6D%65/%66%6F%72%75%6D/helldivers-2-a/625227-helldivers-2-ahk-stratagems.html", "date": "2024-12-20 02:23:00", "forum": "HELLDIVERS 2"}, {"title": "Frameware Release", "link": "https://%75%6E%6B%6E%6F%77%6E%63%68%65%61%74%73.%6D%65/%66%6F%72%75%6D/overwatch/677239-frameware-release.html", "date": "2024-12-20 02:00:00", "forum": "Overwatch"}, {"title": "Stupid&#46;Solutions PVE Cheat", "link": "https://%75%6E%6B%6E%6F%77%6E%63%68%65%61%74%73.%6D%65/%66%6F%72%75%6D/escape-from-tarkov/656746-stupid-solutions-pve-cheat.html", "date": "2024-12-20 01:54:00", "forum": "Escape from Tarkov"}, {"title": "esp testing", "link": "https://%75%6E%6B%6E%6F%77%6E%63%68%65%61%74%73.%6D%65/%66%6F%72%75%6D/rust/677805-esp-testing.html", "date": "2024-12-20 01:53:00", "forum": "Rust"}, {"title": "Ni no Kuni: CrossWorlds", "link": "https://%75%6E%6B%6E%6F%77%6E%63%68%65%61%74%73.%6D%65/%66%6F%72%75%6D/other-mmorpg-and-strategy/500789-ni-kuni-crossworlds.html", "date": "2024-12-20 01:52:00", "forum": "Other MMORPG and Strategy"}, {"title": "multi&#45;threaded autowall", "link": "https://%75%6E%6B%6E%6F%77%6E%63%68%65%61%74%73.%6D%65/%66%6F%72%75%6D/counter-strike-2-a/678001-multi-threaded-autowall.html", "date": "2024-12-20 01:50:00", "forum": "Counter-Strike 2"}, {"title": "X&#45;HOOK for TF2", "link": "https://%75%6E%6B%6E%6F%77%6E%63%68%65%61%74%73.%6D%65/%66%6F%72%75%6D/team-fortress-2-a/288075-hook-tf2.html", "date": "2024-12-20 01:42:00", "forum": "Team Fortress 2"}, {"title": "How do i find and insert CFeatures into my project?", "link": "https://%75%6E%6B%6E%6F%77%6E%63%68%65%61%74%73.%6D%65/%66%6F%72%75%6D/counter-strike-2-a/677630-insert-cfeatures-project.html", "date": "2024-12-20 01:40:00", "forum": "Counter-Strike 2"}, {"title": "Path of Exile 2 Reversal, Structs and Offsets", "link": "https://%75%6E%6B%6E%6F%77%6E%63%68%65%61%74%73.%6D%65/%66%6F%72%75%6D/other-mmorpg-and-strategy/676435-path-exile-2-reversal-structs-offsets.html", "date": "2024-12-20 01:33:00", "forum": "Other MMORPG and Strategy"}, {"title": "Menu showcase thread", "link": "https://%75%6E%6B%6E%6F%77%6E%63%68%65%61%74%73.%6D%65/%66%6F%72%75%6D/counter-strike-2-a/605536-menu-showcase-thread.html", "date": "2024-12-20 01:26:00", "forum": "Counter-Strike 2"}, {"title": "Is Impactdma safe?", "link": "https://%75%6E%6B%6E%6F%77%6E%63%68%65%61%74%73.%6D%65/%66%6F%72%75%6D/pc-hardware/677995-impactdma-safe.html", "date": "2024-12-20 01:16:00", "forum": "PC Hardware"}, {"title": "Delta Force:Hawk Ops Reversal, Structs and Offsets", "link": "https://%75%6E%6B%6E%6F%77%6E%63%68%65%61%74%73.%6D%65/%66%6F%72%75%6D/other-fps-games/653290-delta-force-hawk-ops-reversal-structs-offsets.html", "date": "2024-12-20 01:12:00", "forum": "Other FPS Games"}, {"title": "How to boot/ddos a server/game in ranked?", "link": "https://%75%6E%6B%6E%6F%77%6E%63%68%65%61%74%73.%6D%65/%66%6F%72%75%6D/call-of-duty-black-ops-6-a/677992-boot-ddos-server-game-ranked.html", "date": "2024-12-20 01:06:00", "forum": "Call of Duty: Black Ops 6"}, {"title": "Sunoki's fully updated TB", "link": "https://%75%6E%6B%6E%6F%77%6E%63%68%65%61%74%73.%6D%65/%66%6F%72%75%6D/valorant/669250-sunokis-updated-tb.html", "date": "2024-12-20 01:00:00", "forum": "Valorant"}, {"title": "GTAHaX for 1&#46;70 &#91;External&#93; &#91;Thread 3&#93;", "link": "https://%75%6E%6B%6E%6F%77%6E%63%68%65%61%74%73.%6D%65/%66%6F%72%75%6D/grand-theft-auto-v/461672-gtahax-1-70-external-thread-3-a.html", "date": "2024-12-20 00:57:00", "forum": "Grand Theft Auto V"}, {"title": "Strinova Internal &#40;Aimbot & ESP&#41;", "link": "https://%75%6E%6B%6E%6F%77%6E%63%68%65%61%74%73.%6D%65/%66%6F%72%75%6D/other-fps-games/677105-strinova-internal-aimbot-esp.html", "date": "2024-12-20 00:55:00", "forum": "Other FPS Games"}, {"title": "Valorant Reversal, Structs and Offsets", "link": "https://%75%6E%6B%6E%6F%77%6E%63%68%65%61%74%73.%6D%65/%66%6F%72%75%6D/valorant/385792-valorant-reversal-structs-offsets.html", "date": "2024-12-20 00:54:00", "forum": "Valorant"}, {"title": "Thoughts on renown?", "link": "https://%75%6E%6B%6E%6F%77%6E%63%68%65%61%74%73.%6D%65/%66%6F%72%75%6D/counter-strike-2-a/677880-renown.html", "date": "2024-12-20 00:54:00", "forum": "Counter-Strike 2"}, {"title": "Yet another &#45; Bot Lobby Manager for VM/VPS/NO&#45;VM", "link": "https://%75%6E%6B%6E%6F%77%6E%63%68%65%61%74%73.%6D%65/%66%6F%72%75%6D/call-of-duty-black-ops-6-a/676312-bot-lobby-manager-vm-vps-vm.html", "date": "2024-12-20 00:51:00", "forum": "Call of Duty: Black Ops 6"}, {"title": "Lockdown Protocol External", "link": "https://%75%6E%6B%6E%6F%77%6E%63%68%65%61%74%73.%6D%65/%66%6F%72%75%6D/other-games/667420-lockdown-protocol-external.html", "date": "2024-12-20 00:49:00", "forum": "Other Games"}, {"title": "Marvel Rivals aimbot and esp", "link": "https://%75%6E%6B%6E%6F%77%6E%63%68%65%61%74%73.%6D%65/%66%6F%72%75%6D/marvel-rivals/677440-marvel-rivals-aimbot-esp.html", "date": "2024-12-20 00:49:00", "forum": "Marvel Rivals"}, {"title": "Delta Force hack", "link": "https://%75%6E%6B%6E%6F%77%6E%63%68%65%61%74%73.%6D%65/%66%6F%72%75%6D/other-fps-games/677988-delta-force-hack.html", "date": "2024-12-20 00:43:00", "forum": "Other FPS Games"}, {"title": "All Mouse NoRecoil &#91;Recoil Helpy&#93;&#91;Auto Config&#93;&#91;probably UD&#93;&#91;UNIVERSAL&#93;", "link": "https://%75%6E%6B%6E%6F%77%6E%63%68%65%61%74%73.%6D%65/%66%6F%72%75%6D/rainbow-six-siege/620039-mouse-norecoil-recoil-helpy-auto-config-probably-ud-universal.html", "date": "2024-12-20 00:42:00", "forum": "Rainbow Six Siege"}, {"title": "FiveM Reversal, Structs and Offsets", "link": "https://%75%6E%6B%6E%6F%77%6E%63%68%65%61%74%73.%6D%65/%66%6F%72%75%6D/alternative-online-mods/340232-fivem-reversal-structs-offsets.html", "date": "2024-12-20 00:41:00", "forum": "Alternative Online Mods"}, {"title": "Injection in GTA V for Wine &#43; Crossover", "link": "https://%75%6E%6B%6E%6F%77%6E%63%68%65%61%74%73.%6D%65/%66%6F%72%75%6D/grand-theft-auto-v/653442-injection-gta-wine-crossover.html", "date": "2024-12-20 00:39:00", "forum": "Grand Theft Auto V"}, {"title": "Greedy ass employees", "link": "https://%75%6E%6B%6E%6F%77%6E%63%68%65%61%74%73.%6D%65/%66%6F%72%75%6D/off-topic/677987-greedy-ass-employees.html", "date": "2024-12-20 00:37:00", "forum": "Off Topic"}, {"title": "Offsets needed&#33;", "link": "https://%75%6E%6B%6E%6F%77%6E%63%68%65%61%74%73.%6D%65/%66%6F%72%75%6D/combat-master/677934-offsets.html", "date": "2024-12-20 00:34:00", "forum": "Combat Master"}, {"title": "Rust Reversal, Structs and Offsets", "link": "https://%75%6E%6B%6E%6F%77%6E%63%68%65%61%74%73.%6D%65/%66%6F%72%75%6D/rust/164256-rust-reversal-structs-offsets.html", "date": "2024-12-20 00:31:00", "forum": "Rust"}, {"title": "Call of Duty: Black Ops 6 Reversal, Structs and Offsets", "link": "https://%75%6E%6B%6E%6F%77%6E%63%68%65%61%74%73.%6D%65/%66%6F%72%75%6D/call-of-duty-black-ops-6-a/653959-call-duty-black-ops-6-reversal-structs-offsets.html", "date": "2024-12-20 00:15:00", "forum": "Call of Duty: Black Ops 6"}, {"title": "FSL: local GTAO saves", "link": "https://%75%6E%6B%6E%6F%77%6E%63%68%65%61%74%73.%6D%65/%66%6F%72%75%6D/grand-theft-auto-v/616977-fsl-local-gtao-saves.html", "date": "2024-12-20 00:11:00", "forum": "Grand Theft Auto V"}, {"title": "Deadlock Reversal, Structs and Offsets", "link": "https://%75%6E%6B%6E%6F%77%6E%63%68%65%61%74%73.%6D%65/%66%6F%72%75%6D/deadlock/639185-deadlock-reversal-structs-offsets.html", "date": "2024-12-20 00:11:00", "forum": "Deadlock"}, {"title": "How can I obtain a signing certificate for my driver?", "link": "https://%75%6E%6B%6E%6F%77%6E%63%68%65%61%74%73.%6D%65/%66%6F%72%75%6D/anti-cheat-bypass/677986-obtain-signing-certificate-driver.html", "date": "2024-12-20 00:04:00", "forum": "Anti-Cheat Bypass"}, {"title": "RocketLeague Tool &#91;Function Logger &#43; Object Explorer&#93;", "link": "https://%75%6E%6B%6E%6F%77%6E%63%68%65%61%74%73.%6D%65/%66%6F%72%75%6D/other-games/651431-rocketleague-tool-function-logger-object-explorer.html", "date": "2024-12-20 00:00:00", "forum": "Other Games"}, {"title": "Start Cheating GTA V &#40;Again&#41;", "link": "https://%75%6E%6B%6E%6F%77%6E%63%68%65%61%74%73.%6D%65/%66%6F%72%75%6D/grand-theft-auto-v/677832-start-cheating-gta.html", "date": "2024-12-19 23:50:00", "forum": "Grand Theft Auto V"}, {"title": "Marvel Rivals Reversal, Structs and Offsets", "link": "https://%75%6E%6B%6E%6F%77%6E%63%68%65%61%74%73.%6D%65/%66%6F%72%75%6D/marvel-rivals/652967-marvel-rivals-reversal-structs-offsets.html", "date": "2024-12-19 23:48:00", "forum": "Marvel Rivals"}, {"title": "Apex Legends Reversal, Structs and Offsets", "link": "https://%75%6E%6B%6E%6F%77%6E%63%68%65%61%74%73.%6D%65/%66%6F%72%75%6D/apex-legends/319804-apex-legends-reversal-structs-offsets.html", "date": "2024-12-19 23:47:00", "forum": "Apex Legends"}, {"title": "Why there is no hack for this game?", "link": "https://%75%6E%6B%6E%6F%77%6E%63%68%65%61%74%73.%6D%65/%66%6F%72%75%6D/battlefield-2042-a/597118-hack-game.html", "date": "2024-12-19 23:46:00", "forum": "Battlefield 2042"}, {"title": "Dark and Darker Reversal, Structs and Offsets", "link": "https://%75%6E%6B%6E%6F%77%6E%63%68%65%61%74%73.%6D%65/%66%6F%72%75%6D/other-fps-games/562724-dark-darker-reversal-structs-offsets.html", "date": "2024-12-19 23:35:00", "forum": "Other FPS Games"}, {"title": "&#91;cs2go&#93; &#45; External ESP", "link": "https://%75%6E%6B%6E%6F%77%6E%63%68%65%61%74%73.%6D%65/%66%6F%72%75%6D/counter-strike-2-releases/605464-cs2go-external-esp.html", "date": "2024-12-19 23:33:00", "forum": "Counter-Strike 2 Releases"}]}