{"date": "2025-03-05", "hottest": [{"title": "\u2b50 Want to Make a Difference? Moderators Wanted&#33; \u2b50", "link": "https://%75%6E%6B%6E%6F%77%6E%63%68%65%61%74%73.%6D%65/%66%6F%72%75%6D/information-and-announcements/196807-difference-moderators.html", "date": "2025-03-05 00:11:22", "forum": "information-and-announcements", "reply": "0"}, {"title": "cisco&#45;hook", "link": "https://%75%6E%6B%6E%6F%77%6E%63%68%65%61%74%73.%6D%65/%66%6F%72%75%6D/anti-cheat-bypass/688988-cisco-hook.html", "date": "2025-03-05 00:11:22", "forum": "anti-cheat-bypass", "reply": "22"}, {"title": "Crashing fix for Thugzin's source&#46;", "link": "https://%75%6E%6B%6E%6F%77%6E%63%68%65%61%74%73.%6D%65/%66%6F%72%75%6D/marvel-rivals/688968-crashing-fix-thugzins-source.html", "date": "2025-03-05 00:11:22", "forum": "marvel-rivals", "reply": "13"}, {"title": "Apex yolov11 AI AimAssistant&#40;Logitech Ghub&#41;", "link": "https://%75%6E%6B%6E%6F%77%6E%63%68%65%61%74%73.%6D%65/%66%6F%72%75%6D/apex-legends/688904-apex-yolov11-ai-aimassistant-logitech-ghub.html", "date": "2025-03-05 00:11:22", "forum": "apex-legends", "reply": "21"}, {"title": "efi driver", "link": "https://%75%6E%6B%6E%6F%77%6E%63%68%65%61%74%73.%6D%65/%66%6F%72%75%6D/valorant/688921-efi-driver.html", "date": "2025-03-05 00:11:22", "forum": "valorant", "reply": "13"}, {"title": "\u2b50 Moderators Needed to Expand the Single Player Cheats Section \u2b50", "link": "https://%75%6E%6B%6E%6F%77%6E%63%68%65%61%74%73.%6D%65/%66%6F%72%75%6D/information-and-announcements/676859-moderators-expand-single-player-cheats-section.html", "date": "2025-03-05 00:11:22", "forum": "information-and-announcements", "reply": "0"}, {"title": "SSDs with serials not programmed into their firmware?", "link": "https://%75%6E%6B%6E%6F%77%6E%63%68%65%61%74%73.%6D%65/%66%6F%72%75%6D/valorant/689041-ssds-serials-programmed-firmware.html", "date": "2025-03-05 00:11:22", "forum": "valorant", "reply": "4"}, {"title": "Valorant triggerbot", "link": "https://%75%6E%6B%6E%6F%77%6E%63%68%65%61%74%73.%6D%65/%66%6F%72%75%6D/valorant/689280-valorant-triggerbot.html", "date": "2025-03-05 00:11:22", "forum": "valorant", "reply": "6"}, {"title": "Region lock bypass?", "link": "https://%75%6E%6B%6E%6F%77%6E%63%68%65%61%74%73.%6D%65/%66%6F%72%75%6D/escape-from-tarkov/688922-region-lock-bypass.html", "date": "2025-03-05 00:11:22", "forum": "escape-from-tarkov", "reply": "23"}, {"title": "Is there any way detect EPT Hook?&#40;except for timing check&#41;", "link": "https://%75%6E%6B%6E%6F%77%6E%63%68%65%61%74%73.%6D%65/%66%6F%72%75%6D/anti-cheat-bypass/689037-detect-ept-hook-except-timing-check.html", "date": "2025-03-05 00:11:22", "forum": "anti-cheat-bypass", "reply": "17"}, {"title": "did anyone transferred over?", "link": "https://%75%6E%6B%6E%6F%77%6E%63%68%65%61%74%73.%6D%65/%66%6F%72%75%6D/grand-theft-auto-v/689872-transferred.html", "date": "2025-03-05 03:03:12", "forum": "grand-theft-auto-v", "reply": "19"}], "files": [{"title": "R&#46;E&#46;P&#46;O Simple Menu Version 1&#46;0&#46;0", "link": "https://%75%6E%6B%6E%6F%77%6E%63%68%65%61%74%73.%6D%65/%66%6F%72%75%6D/downloads.php?do=file&id=48866", "date": "2025-03-05 00:11:22", "downloads": "25"}, {"title": "cs2 external multihack v5&#46;2", "link": "https://%75%6E%6B%6E%6F%77%6E%63%68%65%61%74%73.%6D%65/%66%6F%72%75%6D/downloads.php?do=file&id=48864", "date": "2025-03-05 00:11:22", "downloads": "122"}, {"title": "REPO Internal V&#46;2 &#40;localplayer Fix&#41;", "link": "https://%75%6E%6B%6E%6F%77%6E%63%68%65%61%74%73.%6D%65/%66%6F%72%75%6D/downloads.php?do=file&id=48862", "date": "2025-03-05 00:11:22", "downloads": "33"}, {"title": "REPO Internal V&#46;2", "link": "https://%75%6E%6B%6E%6F%77%6E%63%68%65%61%74%73.%6D%65/%66%6F%72%75%6D/downloads.php?do=file&id=48861", "date": "2025-03-05 00:11:22", "downloads": "2"}, {"title": "REPO Internal V&#46;1", "link": "https://%75%6E%6B%6E%6F%77%6E%63%68%65%61%74%73.%6D%65/%66%6F%72%75%6D/downloads.php?do=file&id=48860", "date": "2025-03-05 00:11:22", "downloads": "6"}, {"title": "internal Sigma", "link": "https://%75%6E%6B%6E%6F%77%6E%63%68%65%61%74%73.%6D%65/%66%6F%72%75%6D/downloads.php?do=file&id=48857", "date": "2025-03-05 00:11:22", "downloads": "96"}, {"title": "internal marvel rivals 2&#46;6", "link": "https://%75%6E%6B%6E%6F%77%6E%63%68%65%61%74%73.%6D%65/%66%6F%72%75%6D/downloads.php?do=file&id=48856", "date": "2025-03-05 00:11:22", "downloads": "88"}, {"title": "VTube Studio All DLC v1&#46;31&#46;7", "link": "https://%75%6E%6B%6E%6F%77%6E%63%68%65%61%74%73.%6D%65/%66%6F%72%75%6D/downloads.php?do=file&id=48855", "date": "2025-03-05 00:11:22", "downloads": "5"}, {"title": "dump&#95;0&#46;16&#46;1&#46;35328", "link": "https://%75%6E%6B%6E%6F%77%6E%63%68%65%61%74%73.%6D%65/%66%6F%72%75%6D/downloads.php?do=file&id=48853", "date": "2025-03-05 00:11:22", "downloads": "6"}, {"title": "ReadyOrNot internal", "link": "https://%75%6E%6B%6E%6F%77%6E%63%68%65%61%74%73.%6D%65/%66%6F%72%75%6D/downloads.php?do=file&id=48852", "date": "2025-03-05 00:11:22", "downloads": "45"}], "latest": [{"title": "Destiny 2 Inventory", "link": "https://%75%6E%6B%6E%6F%77%6E%63%68%65%61%74%73.%6D%65/%66%6F%72%75%6D/other-fps-games/668891-destiny-2-inventory.html", "date": "2025-03-05 03:22:00", "forum": "Other FPS Games"}, {"title": "Ban evade", "link": "https://%75%6E%6B%6E%6F%77%6E%63%68%65%61%74%73.%6D%65/%66%6F%72%75%6D/garry-s-mod/689730-ban-evade.html", "date": "2025-03-05 03:21:00", "forum": "Garry's Mod"}, {"title": "Marvel Rivals TriggerBot & AimAssist &#40;MouseBased Undetected&#41;", "link": "https://%75%6E%6B%6E%6F%77%6E%63%68%65%61%74%73.%6D%65/%66%6F%72%75%6D/marvel-rivals/678761-marvel-rivals-triggerbot-aimassist-mousebased-undetected.html", "date": "2025-03-05 03:21:00", "forum": "Marvel Rivals"}, {"title": "Nika Read Only", "link": "https://%75%6E%6B%6E%6F%77%6E%63%68%65%61%74%73.%6D%65/%66%6F%72%75%6D/apex-legends/640853-nika-read.html", "date": "2025-03-05 03:16:00", "forum": "Apex Legends"}, {"title": "Valorant insta headshot AIMBOT&#91;UNDETECTED&#93;", "link": "https://%75%6E%6B%6E%6F%77%6E%63%68%65%61%74%73.%6D%65/%66%6F%72%75%6D/valorant/688675-valorant-insta-headshot-aimbot-undetected.html", "date": "2025-03-05 03:09:00", "forum": "Valorant"}, {"title": "GTA5&#95;Enchanced Basic DMA Tool", "link": "https://%75%6E%6B%6E%6F%77%6E%63%68%65%61%74%73.%6D%65/%66%6F%72%75%6D/grand-theft-auto-v/689945-gta5_enchanced-basic-dma-tool.html", "date": "2025-03-05 02:56:00", "forum": "Grand Theft Auto V"}, {"title": "All Mouse NoRecoil &#91;Recoil Helpy&#93;&#91;Auto Config&#93;&#91;probably UD&#93;&#91;UNIVERSAL&#93;", "link": "https://%75%6E%6B%6E%6F%77%6E%63%68%65%61%74%73.%6D%65/%66%6F%72%75%6D/rainbow-six-siege/620039-mouse-norecoil-recoil-helpy-auto-config-probably-ud-universal.html", "date": "2025-03-05 03:00:00", "forum": "Rainbow Six Siege"}, {"title": "Simple Module Editor", "link": "https://%75%6E%6B%6E%6F%77%6E%63%68%65%61%74%73.%6D%65/%66%6F%72%75%6D/elite-dangerous/573662-simple-module-editor.html", "date": "2025-03-05 02:59:00", "forum": "Elite: Dangerous"}, {"title": "1&#46;21 Mappings", "link": "https://%75%6E%6B%6E%6F%77%6E%63%68%65%61%74%73.%6D%65/%66%6F%72%75%6D/minecraft/688587-1-21-mappings.html", "date": "2025-03-05 02:53:00", "forum": "Minecraft"}, {"title": "Spring & Easter Banner Contest 2025", "link": "https://%75%6E%6B%6E%6F%77%6E%63%68%65%61%74%73.%6D%65/%66%6F%72%75%6D/general-graphics/689496-spring-easter-banner-contest-2025-a.html", "date": "2025-03-05 02:51:00", "forum": "General Graphics"}, {"title": "yup its real unban me for 10$", "link": "https://%75%6E%6B%6E%6F%77%6E%63%68%65%61%74%73.%6D%65/%66%6F%72%75%6D/valorant/689795-yup-real-unban-10-a.html", "date": "2025-03-05 02:48:00", "forum": "Valorant"}, {"title": "More efficient UpdateEntity", "link": "https://%75%6E%6B%6E%6F%77%6E%63%68%65%61%74%73.%6D%65/%66%6F%72%75%6D/alternative-online-mods/689585-efficient-updateentity.html", "date": "2025-03-05 02:42:00", "forum": "Alternative Online Mods"}, {"title": "arduino leonardo &#45; usb host shield", "link": "https://%75%6E%6B%6E%6F%77%6E%63%68%65%61%74%73.%6D%65/%66%6F%72%75%6D/valorant/689810-arduino-leonardo-usb-host-shield.html", "date": "2025-03-05 02:41:00", "forum": "Valorant"}, {"title": "emoticons", "link": "https://%75%6E%6B%6E%6F%77%6E%63%68%65%61%74%73.%6D%65/%66%6F%72%75%6D/off-topic/685820-emoticons.html", "date": "2025-03-05 02:39:00", "forum": "Off Topic"}, {"title": "msi val spoof?", "link": "https://%75%6E%6B%6E%6F%77%6E%63%68%65%61%74%73.%6D%65/%66%6F%72%75%6D/valorant/686894-msi-val-spoof.html", "date": "2025-03-05 02:33:00", "forum": "Valorant"}, {"title": "MarlBot fix v1&#46;6&#46;1&#45;dev1", "link": "https://%75%6E%6B%6E%6F%77%6E%63%68%65%61%74%73.%6D%65/%66%6F%72%75%6D/other-games/680404-marlbot-fix-v1-6-1-dev1.html", "date": "2025-03-05 02:28:00", "forum": "Other Games"}, {"title": "Spidey Internal", "link": "https://%75%6E%6B%6E%6F%77%6E%63%68%65%61%74%73.%6D%65/%66%6F%72%75%6D/marvel-rivals/688727-spidey-internal.html", "date": "2025-03-05 02:24:00", "forum": "Marvel Rivals"}, {"title": "C&#35; From C&#43;&#43;", "link": "https://%75%6E%6B%6E%6F%77%6E%63%68%65%61%74%73.%6D%65/%66%6F%72%75%6D/general-programming-and-reversing/689933-c-from-c.html", "date": "2025-03-05 02:24:00", "forum": "General Programming and Reversing"}, {"title": "Sunoki's fully updated TB", "link": "https://%75%6E%6B%6E%6F%77%6E%63%68%65%61%74%73.%6D%65/%66%6F%72%75%6D/valorant/669250-sunokis-updated-tb.html", "date": "2025-03-05 02:17:00", "forum": "Valorant"}, {"title": "Get out of custody non/host", "link": "https://%75%6E%6B%6E%6F%77%6E%63%68%65%61%74%73.%6D%65/%66%6F%72%75%6D/payday-2-a/687913-custody-host.html", "date": "2025-03-05 02:16:00", "forum": "Payday 2"}, {"title": "Soldier 76 Complete Recoil Control", "link": "https://%75%6E%6B%6E%6F%77%6E%63%68%65%61%74%73.%6D%65/%66%6F%72%75%6D/overwatch/675745-soldier-76-complete-recoil-control.html", "date": "2025-03-05 01:52:00", "forum": "Overwatch"}, {"title": "Hack for CSSO 1&#46;1", "link": "https://%75%6E%6B%6E%6F%77%6E%63%68%65%61%74%73.%6D%65/%66%6F%72%75%6D/counterstrike-source/689920-hack-csso-1-1-a.html", "date": "2025-03-05 01:49:00", "forum": "CounterStrike Source"}, {"title": "If anyone can help resolve the crash issues during gameplay, I would greatly apprecia", "link": "https://%75%6E%6B%6E%6F%77%6E%63%68%65%61%74%73.%6D%65/%66%6F%72%75%6D/marvel-rivals/689627-help-resolve-crash-issues-gameplay-greatly-apprecia.html", "date": "2025-03-05 01:45:00", "forum": "Marvel Rivals"}, {"title": "Fallout 76 BA2 Cheat Collection", "link": "https://%75%6E%6B%6E%6F%77%6E%63%68%65%61%74%73.%6D%65/%66%6F%72%75%6D/other-fps-games/519969-fallout-76-ba2-cheat-collection.html", "date": "2025-03-05 01:41:00", "forum": "Other FPS Games"}, {"title": "&#91;DMA&#93; Can't read the module with kernel anticheat open", "link": "https://%75%6E%6B%6E%6F%77%6E%63%68%65%61%74%73.%6D%65/%66%6F%72%75%6D/counter-strike-2-a/689928-dma-cant-read-module-kernel-anticheat.html", "date": "2025-03-05 01:40:00", "forum": "Counter-Strike 2"}, {"title": "Quick Peek macro", "link": "https://%75%6E%6B%6E%6F%77%6E%63%68%65%61%74%73.%6D%65/%66%6F%72%75%6D/rainbow-six-siege/689927-quick-peek-macro.html", "date": "2025-03-05 01:37:00", "forum": "Rainbow Six Siege"}, {"title": "RiotLogin &#45; Automatic Riot Client Login Tool", "link": "https://%75%6E%6B%6E%6F%77%6E%63%68%65%61%74%73.%6D%65/%66%6F%72%75%6D/league-of-legends/597675-riotlogin-automatic-riot-client-login-tool.html", "date": "2025-03-05 01:34:00", "forum": "League of Legends"}, {"title": "YimMenu&#46;dll 1&#46;70 update", "link": "https://%75%6E%6B%6E%6F%77%6E%63%68%65%61%74%73.%6D%65/%66%6F%72%75%6D/grand-theft-auto-v/678007-yimmenu-dll-1-70-update.html", "date": "2025-03-05 01:31:00", "forum": "Grand Theft Auto V"}, {"title": "Delta Force:Hawk Ops Reversal, Structs and Offsets", "link": "https://%75%6E%6B%6E%6F%77%6E%63%68%65%61%74%73.%6D%65/%66%6F%72%75%6D/other-fps-games/653290-delta-force-hawk-ops-reversal-structs-offsets.html", "date": "2025-03-05 01:29:00", "forum": "Other FPS Games"}, {"title": "Valorant triggerbot", "link": "https://%75%6E%6B%6E%6F%77%6E%63%68%65%61%74%73.%6D%65/%66%6F%72%75%6D/valorant/689280-valorant-triggerbot.html", "date": "2025-03-05 01:27:00", "forum": "Valorant"}, {"title": "Unity GUI", "link": "https://%75%6E%6B%6E%6F%77%6E%63%68%65%61%74%73.%6D%65/%66%6F%72%75%6D/unity/689923-unity-gui.html", "date": "2025-03-05 01:25:00", "forum": "Unity"}, {"title": "eventlog", "link": "https://%75%6E%6B%6E%6F%77%6E%63%68%65%61%74%73.%6D%65/%66%6F%72%75%6D/alternative-online-mods/689885-eventlog.html", "date": "2025-03-05 01:15:00", "forum": "Alternative Online Mods"}, {"title": "CS2External Aim/Esp/Misc", "link": "https://%75%6E%6B%6E%6F%77%6E%63%68%65%61%74%73.%6D%65/%66%6F%72%75%6D/counter-strike-2-releases/673859-cs2external-aim-esp-misc.html", "date": "2025-03-05 01:06:00", "forum": "Counter-Strike 2 Releases"}, {"title": "ENSD &#40;Trailblazers v4&#46;1&#46;0&#46;0&#41;", "link": "https://%75%6E%6B%6E%6F%77%6E%63%68%65%61%74%73.%6D%65/%66%6F%72%75%6D/elite-dangerous/658785-ensd-trailblazers-v4-1-0-0-a.html", "date": "2025-03-05 01:04:00", "forum": "Elite: Dangerous"}, {"title": "YimMenu &#91;1&#46;69 &#45; b3351&#93;", "link": "https://%75%6E%6B%6E%6F%77%6E%63%68%65%61%74%73.%6D%65/%66%6F%72%75%6D/grand-theft-auto-v/476972-yimmenu-1-69-b3351.html", "date": "2025-03-05 01:04:00", "forum": "Grand Theft Auto V"}, {"title": "Cheat Legit External &#40;UPDATE&#41; TKZ CREDITS", "link": "https://%75%6E%6B%6E%6F%77%6E%63%68%65%61%74%73.%6D%65/%66%6F%72%75%6D/counter-strike-2-a/683283-cheat-legit-external-update-tkz-credits.html", "date": "2025-03-05 01:00:00", "forum": "Counter-Strike 2"}, {"title": "SoT Datamining &#43; Unreleased/Unused Assets", "link": "https://%75%6E%6B%6E%6F%77%6E%63%68%65%61%74%73.%6D%65/%66%6F%72%75%6D/sea-of-thieves/624262-sot-datamining-unreleased-unused-assets.html", "date": "2025-03-05 01:00:00", "forum": "Sea of Thieves"}, {"title": "Sigma Rivals &#124; Gooner edition", "link": "https://%75%6E%6B%6E%6F%77%6E%63%68%65%61%74%73.%6D%65/%66%6F%72%75%6D/marvel-rivals/689792-sigma-rivals-gooner-edition.html", "date": "2025-03-05 00:54:00", "forum": "Marvel Rivals"}, {"title": "CS2 External Basic Multihack", "link": "https://%75%6E%6B%6E%6F%77%6E%63%68%65%61%74%73.%6D%65/%66%6F%72%75%6D/counter-strike-2-a/686341-cs2-external-basic-multihack.html", "date": "2025-03-05 00:49:00", "forum": "Counter-Strike 2"}, {"title": "Get right FiveM version &#40;bypass replaceExecutable&#41;", "link": "https://%75%6E%6B%6E%6F%77%6E%63%68%65%61%74%73.%6D%65/%66%6F%72%75%6D/alternative-online-mods/689318-fivem-version-bypass-replaceexecutable.html", "date": "2025-03-05 00:43:00", "forum": "Alternative Online Mods"}, {"title": "DayZ Reversal, Structs and Offsets", "link": "https://%75%6E%6B%6E%6F%77%6E%63%68%65%61%74%73.%6D%65/%66%6F%72%75%6D/dayz-sa/104269-dayz-reversal-structs-offsets.html", "date": "2025-03-05 00:38:00", "forum": "DayZ SA"}, {"title": "Killing Floor 2 External Hack", "link": "https://%75%6E%6B%6E%6F%77%6E%63%68%65%61%74%73.%6D%65/%66%6F%72%75%6D/other-games/673060-killing-floor-2-external-hack.html", "date": "2025-03-05 00:36:00", "forum": "Other Games"}, {"title": "What is wrong with that C&#43;&#43; code &#40;Triggerbot&#41; ?", "link": "https://%75%6E%6B%6E%6F%77%6E%63%68%65%61%74%73.%6D%65/%66%6F%72%75%6D/counter-strike-2-a/689410-wrong-code-triggerbot.html", "date": "2025-03-05 00:36:00", "forum": "Counter-Strike 2"}, {"title": "\ud83d\ude80 &#91;FREE RELEASE&#93; Valorant DMA Firmware for PCILeech &#45; Open Source, Low Latency, Anti", "link": "https://%75%6E%6B%6E%6F%77%6E%63%68%65%61%74%73.%6D%65/%66%6F%72%75%6D/valorant/689840-free-release-valorant-dma-firmware-pcileech-source-low-latency-anti.html", "date": "2025-03-05 00:33:00", "forum": "Valorant"}, {"title": "UD Injector/CE", "link": "https://%75%6E%6B%6E%6F%77%6E%63%68%65%61%74%73.%6D%65/%66%6F%72%75%6D/marvel-rivals/686797-ud-injector-ce.html", "date": "2025-03-05 00:33:00", "forum": "Marvel Rivals"}, {"title": "Call of Duty: Black Ops 6 Reversal, Structs and Offsets", "link": "https://%75%6E%6B%6E%6F%77%6E%63%68%65%61%74%73.%6D%65/%66%6F%72%75%6D/call-of-duty-black-ops-6-a/653959-call-duty-black-ops-6-reversal-structs-offsets.html", "date": "2025-03-05 00:32:00", "forum": "Call of Duty: Black Ops 6"}, {"title": "Apex Legends Reversal, Structs and Offsets", "link": "https://%75%6E%6B%6E%6F%77%6E%63%68%65%61%74%73.%6D%65/%66%6F%72%75%6D/apex-legends/319804-apex-legends-reversal-structs-offsets.html", "date": "2025-03-05 00:31:00", "forum": "Apex Legends"}, {"title": "&#91;Division 2&#93;aim&#45;bot", "link": "https://%75%6E%6B%6E%6F%77%6E%63%68%65%61%74%73.%6D%65/%66%6F%72%75%6D/tom-clancy-s-the-division/689204-division-2-aim-bot.html", "date": "2025-03-05 00:28:00", "forum": "Tom Clancy's The Division"}, {"title": "CR3 encryption in Finals", "link": "https://%75%6E%6B%6E%6F%77%6E%63%68%65%61%74%73.%6D%65/%66%6F%72%75%6D/anti-cheat-bypass/689898-cr3-encryption-finals.html", "date": "2025-03-05 00:27:00", "forum": "Anti-Cheat Bypass"}, {"title": "Ready Or Not Internal Cheat", "link": "https://%75%6E%6B%6E%6F%77%6E%63%68%65%61%74%73.%6D%65/%66%6F%72%75%6D/other-fps-games/625051-ready-internal-cheat.html", "date": "2025-03-05 00:26:00", "forum": "Other FPS Games"}, {"title": "GamerFun AI Menu: All mouse Aimbot, Triggerbot & Recoil Control Using LGUB Drivers", "link": "https://%75%6E%6B%6E%6F%77%6E%63%68%65%61%74%73.%6D%65/%66%6F%72%75%6D/rainbow-six-siege/671029-gamerfun-ai-menu-mouse-aimbot-triggerbot-recoil-control-using-lgub-drivers.html", "date": "2025-03-05 00:26:00", "forum": "Rainbow Six Siege"}, {"title": "Gta migration error", "link": "https://%75%6E%6B%6E%6F%77%6E%63%68%65%61%74%73.%6D%65/%66%6F%72%75%6D/grand-theft-auto-v/689887-gta-migration-error.html", "date": "2025-03-05 00:09:00", "forum": "Grand Theft Auto V"}, {"title": "GTA V Online PC Gets Next Gen 2025 &#45; Update Coming Next", "link": "https://%75%6E%6B%6E%6F%77%6E%63%68%65%61%74%73.%6D%65/%66%6F%72%75%6D/grand-theft-auto-v/670008-gta-online-pc-gen-2025-update-coming.html", "date": "2025-03-05 00:08:00", "forum": "Grand Theft Auto V"}, {"title": "R&#46;E&#46;P&#46;O Basic Internal", "link": "https://%75%6E%6B%6E%6F%77%6E%63%68%65%61%74%73.%6D%65/%66%6F%72%75%6D/other-fps-games/689804-basic-internal.html", "date": "2025-03-05 00:08:00", "forum": "Other FPS Games"}, {"title": "topic for collecting data from migrated and non&#45;migrated accounts", "link": "https://%75%6E%6B%6E%6F%77%6E%63%68%65%61%74%73.%6D%65/%66%6F%72%75%6D/grand-theft-auto-v/689890-topic-collecting-data-migrated-migrated-accounts.html", "date": "2025-03-05 00:06:00", "forum": "Grand Theft Auto V"}, {"title": "did anyone transferred over?", "link": "https://%75%6E%6B%6E%6F%77%6E%63%68%65%61%74%73.%6D%65/%66%6F%72%75%6D/grand-theft-auto-v/689872-transferred.html", "date": "2025-03-05 00:05:00", "forum": "Grand Theft Auto V"}, {"title": "simple internal", "link": "https://%75%6E%6B%6E%6F%77%6E%63%68%65%61%74%73.%6D%65/%66%6F%72%75%6D/marvel-rivals/680544-simple-internal.html", "date": "2025-03-05 00:01:00", "forum": "Marvel Rivals"}, {"title": "nightmode for externals", "link": "https://%75%6E%6B%6E%6F%77%6E%63%68%65%61%74%73.%6D%65/%66%6F%72%75%6D/counter-strike-2-a/686426-nightmode-externals.html", "date": "2025-03-04 23:59:00", "forum": "Counter-Strike 2"}, {"title": "External aimbot prediction", "link": "https://%75%6E%6B%6E%6F%77%6E%63%68%65%61%74%73.%6D%65/%66%6F%72%75%6D/counter-strike-2-a/689702-external-aimbot-prediction.html", "date": "2025-03-04 23:59:00", "forum": "Counter-Strike 2"}, {"title": "CSS x64 fully&#45;featured cheat &#43; sourcecode", "link": "https://%75%6E%6B%6E%6F%77%6E%63%68%65%61%74%73.%6D%65/%66%6F%72%75%6D/counterstrike-source/688352-css-x64-featured-cheat-sourcecode.html", "date": "2025-03-04 23:58:00", "forum": "CounterStrike Source"}, {"title": "Rust Reversal, Structs and Offsets", "link": "https://%75%6E%6B%6E%6F%77%6E%63%68%65%61%74%73.%6D%65/%66%6F%72%75%6D/rust/164256-rust-reversal-structs-offsets.html", "date": "2025-03-04 23:58:00", "forum": "Rust"}]}